{"localidades":{"SAL001":{"nombre":"Capital","id":"001","votacion":{"mesas":{"total":1044,"escrutadas":1044,"porcentaje":100},"votos":{"total":272789,"escrutados":358672,"porcentaje":100},"partidos_politicos":{"0":{"id":"536","nombre":"UNION POR LA REPUBLICA - FRENTE POR LA JUSTICIA","fuerza_politica":"a definir por pablo","votos":86830,"porcentaje":"37.62","entra":"si"},"1":{"id":"014","nombre":"PARTIDO OBRERO","fuerza_politica":"a definir por pablo","votos":19801,"porcentaje":"8.58","entra":"si"},"2":{"id":"002","nombre":"PARTIDO JUSTICIALISTA","fuerza_politica":"a definir por pablo","votos":19675,"porcentaje":"8.52","entra":"si","internas":[{"lista":"3085","nombre":"LISTA:  LEALTAD 17 DE OCTUBRE - LETRA:  C","votos":12074,"porcentaje":"61.37"},{"lista":"3084","nombre":"LISTA:  EL CAMBIO SOMOS NOSOTROS  - LETRA:  B","votos":7601,"porcentaje":"38.63"}]},"3":{"id":"200","nombre":"MEMORIA Y MOVILIZACION SOCIAL","fuerza_politica":"a definir por pablo","votos":13469,"porcentaje":"5.84","entra":"si"},"4":{"id":"038","nombre":"MOVIMIENTO SOCIALISTA DE LOS TRABAJADORES (MST)","fuerza_politica":"a definir por pablo","votos":10718,"porcentaje":"4.64","entra":"si"},"5":{"id":"203","nombre":"SALTA SOMOS TODOS","fuerza_politica":"a definir por pablo","votos":10542,"porcentaje":"4.57","entra":"si"},"6":{"id":"155","nombre":"PARTIDO RENOVADOR DE SALTA","fuerza_politica":"a definir por pablo","votos":9587,"porcentaje":"4.15","entra":"si"},"7":{"id":"060","nombre":"MOVIMIENTO INDEPENDIENTE JUSTICIA Y DIGNIDAD","fuerza_politica":"a definir por pablo","votos":9183,"porcentaje":"3.98","entra":"si"},"8":{"id":"216","nombre":"FRENTE PLURAL","fuerza_politica":"a definir por pablo","votos":8641,"porcentaje":"3.74","entra":"si"},"9":{"id":"054","nombre":"PARTIDO DE LA VICTORIA","fuerza_politica":"a definir por pablo","votos":7353,"porcentaje":"3.19","entra":"si"},"10":{"id":"535","nombre":"FRENTE POPULAR SALTE\u00d1O","fuerza_politica":"a definir por pablo","votos":5502,"porcentaje":"2.38","entra":"si"},"blanco":{"id":"blanco","votos":29504,"porcentaje":"10.82"},"nulos":{"id":"nulos","votos":13126,"porcentaje":"4.81"},"recurridos":{"id":"recurridos","votos":28858,"porcentaje":"10.58"}}}},"SAL002":{"nombre":"La Caldera","id":"002","votacion":{"mesas":{"total":23,"escrutadas":23,"porcentaje":100},"votos":{"total":5296,"escrutados":6976,"porcentaje":100},"partidos_politicos":{"0":{"id":"536","nombre":"UNION POR LA REPUBLICA - FRENTE POR LA JUSTICIA","fuerza_politica":"a definir por pablo","votos":1688,"porcentaje":"37.62","entra":"si"},"1":{"id":"002","nombre":"PARTIDO JUSTICIALISTA","fuerza_politica":"a definir por pablo","votos":387,"porcentaje":"8.62","entra":"si","internas":[{"lista":"3085","nombre":"LISTA:  LEALTAD 17 DE OCTUBRE - LETRA:  C","votos":232,"porcentaje":"59.95"},{"lista":"3084","nombre":"LISTA:  EL CAMBIO SOMOS NOSOTROS  - LETRA:  B","votos":155,"porcentaje":"40.05"}]},"2":{"id":"014","nombre":"PARTIDO OBRERO","fuerza_politica":"a definir por pablo","votos":385,"porcentaje":"8.58","entra":"si"},"3":{"id":"200","nombre":"MEMORIA Y MOVILIZACION SOCIAL","fuerza_politica":"a definir por pablo","votos":263,"porcentaje":"5.86","entra":"si"},"4":{"id":"038","nombre":"MOVIMIENTO SOCIALISTA DE LOS TRABAJADORES (MST)","fuerza_politica":"a definir por pablo","votos":210,"porcentaje":"4.68","entra":"si"},"5":{"id":"216","nombre":"FRENTE PLURAL","fuerza_politica":"a definir por pablo","votos":190,"porcentaje":"4.23","entra":"si"},"6":{"id":"203","nombre":"SALTA SOMOS TODOS","fuerza_politica":"a definir por pablo","votos":187,"porcentaje":"4.17","entra":"si"},"7":{"id":"155","nombre":"PARTIDO RENOVADOR DE SALTA","fuerza_politica":"a definir por pablo","votos":186,"porcentaje":"4.15","entra":"si"},"8":{"id":"060","nombre":"MOVIMIENTO INDEPENDIENTE JUSTICIA Y DIGNIDAD","fuerza_politica":"a definir por pablo","votos":173,"porcentaje":"3.86","entra":"si"},"9":{"id":"054","nombre":"PARTIDO DE LA VICTORIA","fuerza_politica":"a definir por pablo","votos":140,"porcentaje":"3.12","entra":"si"},"10":{"id":"535","nombre":"FRENTE POPULAR SALTE\u00d1O","fuerza_politica":"a definir por pablo","votos":107,"porcentaje":"2.38","entra":"si"},"blanco":{"id":"blanco","votos":571,"porcentaje":"10.78"},"nulos":{"id":"nulos","votos":252,"porcentaje":"4.76"},"recurridos":{"id":"recurridos","votos":557,"porcentaje":"10.52"}}}},"SAL003":{"nombre":"General G\u00fcemes","id":"003","votacion":{"mesas":{"total":93,"escrutadas":93,"porcentaje":100},"votos":{"total":23918,"escrutados":31464,"porcentaje":100},"partidos_politicos":{"0":{"id":"536","nombre":"UNION POR LA REPUBLICA - FRENTE POR LA JUSTICIA","fuerza_politica":"a definir por pablo","votos":7622,"porcentaje":"37.66","entra":"si"},"1":{"id":"014","nombre":"PARTIDO OBRERO","fuerza_politica":"a definir por pablo","votos":1735,"porcentaje":"8.57","entra":"si"},"2":{"id":"002","nombre":"PARTIDO JUSTICIALISTA","fuerza_politica":"a definir por pablo","votos":1723,"porcentaje":"8.51","entra":"si","internas":[{"lista":"3085","nombre":"LISTA:  LEALTAD 17 DE OCTUBRE - LETRA:  C","votos":1048,"porcentaje":"60.82"},{"lista":"3084","nombre":"LISTA:  EL CAMBIO SOMOS NOSOTROS  - LETRA:  B","votos":675,"porcentaje":"39.18"}]},"3":{"id":"200","nombre":"MEMORIA Y MOVILIZACION SOCIAL","fuerza_politica":"a definir por pablo","votos":1178,"porcentaje":"5.82","entra":"si"},"4":{"id":"038","nombre":"MOVIMIENTO SOCIALISTA DE LOS TRABAJADORES (MST)","fuerza_politica":"a definir por pablo","votos":935,"porcentaje":"4.62","entra":"si"},"5":{"id":"203","nombre":"SALTA SOMOS TODOS","fuerza_politica":"a definir por pablo","votos":922,"porcentaje":"4.56","entra":"si"},"6":{"id":"155","nombre":"PARTIDO RENOVADOR DE SALTA","fuerza_politica":"a definir por pablo","votos":839,"porcentaje":"4.15","entra":"si"},"7":{"id":"060","nombre":"MOVIMIENTO INDEPENDIENTE JUSTICIA Y DIGNIDAD","fuerza_politica":"a definir por pablo","votos":806,"porcentaje":"3.98","entra":"si"},"8":{"id":"216","nombre":"FRENTE PLURAL","fuerza_politica":"a definir por pablo","votos":764,"porcentaje":"3.78","entra":"si"},"9":{"id":"054","nombre":"PARTIDO DE LA VICTORIA","fuerza_politica":"a definir por pablo","votos":647,"porcentaje":"3.20","entra":"si"},"10":{"id":"535","nombre":"FRENTE POPULAR SALTE\u00d1O","fuerza_politica":"a definir por pablo","votos":480,"porcentaje":"2.37","entra":"si"},"blanco":{"id":"blanco","votos":2587,"porcentaje":"10.82"},"nulos":{"id":"nulos","votos":1149,"porcentaje":"4.80"},"recurridos":{"id":"recurridos","votos":2531,"porcentaje":"10.58"}}}},"SAL004":{"nombre":"Met\u00e1n","id":"004","votacion":{"mesas":{"total":91,"escrutadas":91,"porcentaje":100},"votos":{"total":22317,"escrutados":29377,"porcentaje":100},"partidos_politicos":{"0":{"id":"536","nombre":"UNION POR LA REPUBLICA - FRENTE POR LA JUSTICIA","fuerza_politica":"a definir por pablo","votos":7068,"porcentaje":"37.41","entra":"si"},"1":{"id":"002","nombre":"PARTIDO JUSTICIALISTA","fuerza_politica":"a definir por pablo","votos":1641,"porcentaje":"8.69","entra":"si","internas":[{"lista":"3085","nombre":"LISTA:  LEALTAD 17 DE OCTUBRE - LETRA:  C","votos":993,"porcentaje":"60.51"},{"lista":"3084","nombre":"LISTA:  EL CAMBIO SOMOS NOSOTROS  - LETRA:  B","votos":648,"porcentaje":"39.49"}]},"2":{"id":"014","nombre":"PARTIDO OBRERO","fuerza_politica":"a definir por pablo","votos":1619,"porcentaje":"8.57","entra":"si"},"3":{"id":"200","nombre":"MEMORIA Y MOVILIZACION SOCIAL","fuerza_politica":"a definir por pablo","votos":1098,"porcentaje":"5.81","entra":"si"},"4":{"id":"203","nombre":"SALTA SOMOS TODOS","fuerza_politica":"a definir por pablo","votos":889,"porcentaje":"4.71","entra":"si"},"5":{"id":"038","nombre":"MOVIMIENTO SOCIALISTA DE LOS TRABAJADORES (MST)","fuerza_politica":"a definir por pablo","votos":882,"porcentaje":"4.67","entra":"si"},"6":{"id":"155","nombre":"PARTIDO RENOVADOR DE SALTA","fuerza_politica":"a definir por pablo","votos":782,"porcentaje":"4.14","entra":"si"},"7":{"id":"060","nombre":"MOVIMIENTO INDEPENDIENTE JUSTICIA Y DIGNIDAD","fuerza_politica":"a definir por pablo","votos":756,"porcentaje":"4.00","entra":"si"},"8":{"id":"216","nombre":"FRENTE PLURAL","fuerza_politica":"a definir por pablo","votos":690,"porcentaje":"3.65","entra":"si"},"9":{"id":"054","nombre":"PARTIDO DE LA VICTORIA","fuerza_politica":"a definir por pablo","votos":607,"porcentaje":"3.21","entra":"si"},"10":{"id":"535","nombre":"FRENTE POPULAR SALTE\u00d1O","fuerza_politica":"a definir por pablo","votos":448,"porcentaje":"2.37","entra":"si"},"blanco":{"id":"blanco","votos":2411,"porcentaje":"10.80"},"nulos":{"id":"nulos","votos":1072,"porcentaje":"4.80"},"recurridos":{"id":"recurridos","votos":2354,"porcentaje":"10.55"}}}},"SAL005":{"nombre":"Anta","id":"005","votacion":{"mesas":{"total":121,"escrutadas":121,"porcentaje":100},"votos":{"total":28965,"escrutados":38089,"porcentaje":100},"partidos_politicos":{"0":{"id":"536","nombre":"UNION POR LA REPUBLICA - FRENTE POR LA JUSTICIA","fuerza_politica":"a definir por pablo","votos":9243,"porcentaje":"37.68","entra":"si"},"1":{"id":"002","nombre":"PARTIDO JUSTICIALISTA","fuerza_politica":"a definir por pablo","votos":2121,"porcentaje":"8.65","entra":"si","internas":[{"lista":"3085","nombre":"LISTA:  LEALTAD 17 DE OCTUBRE - LETRA:  C","votos":1295,"porcentaje":"61.06"},{"lista":"3084","nombre":"LISTA:  EL CAMBIO SOMOS NOSOTROS  - LETRA:  B","votos":826,"porcentaje":"38.94"}]},"2":{"id":"014","nombre":"PARTIDO OBRERO","fuerza_politica":"a definir por pablo","votos":2101,"porcentaje":"8.57","entra":"si"},"3":{"id":"200","nombre":"MEMORIA Y MOVILIZACION SOCIAL","fuerza_politica":"a definir por pablo","votos":1429,"porcentaje":"5.83","entra":"si"},"4":{"id":"038","nombre":"MOVIMIENTO SOCIALISTA DE LOS TRABAJADORES (MST)","fuerza_politica":"a definir por pablo","votos":1136,"porcentaje":"4.63","entra":"si"},"5":{"id":"203","nombre":"SALTA SOMOS TODOS","fuerza_politica":"a definir por pablo","votos":1116,"porcentaje":"4.55","entra":"si"},"6":{"id":"155","nombre":"PARTIDO RENOVADOR DE SALTA","fuerza_politica":"a definir por pablo","votos":1005,"porcentaje":"4.10","entra":"si"},"7":{"id":"060","nombre":"MOVIMIENTO INDEPENDIENTE JUSTICIA Y DIGNIDAD","fuerza_politica":"a definir por pablo","votos":972,"porcentaje":"3.96","entra":"si"},"8":{"id":"216","nombre":"FRENTE PLURAL","fuerza_politica":"a definir por pablo","votos":919,"porcentaje":"3.75","entra":"si"},"9":{"id":"054","nombre":"PARTIDO DE LA VICTORIA","fuerza_politica":"a definir por pablo","votos":775,"porcentaje":"3.16","entra":"si"},"10":{"id":"535","nombre":"FRENTE POPULAR SALTE\u00d1O","fuerza_politica":"a definir por pablo","votos":584,"porcentaje":"2.38","entra":"si"},"blanco":{"id":"blanco","votos":3128,"porcentaje":"10.80"},"nulos":{"id":"nulos","votos":1386,"porcentaje":"4.79"},"recurridos":{"id":"recurridos","votos":3050,"porcentaje":"10.53"}}}},"SAL006":{"nombre":"Rivadavia","id":"006","votacion":{"mesas":{"total":68,"escrutadas":68,"porcentaje":100},"votos":{"total":14699,"escrutados":19380,"porcentaje":100},"partidos_politicos":{"0":{"id":"536","nombre":"UNION POR LA REPUBLICA - FRENTE POR LA JUSTICIA","fuerza_politica":"a definir por pablo","votos":4733,"porcentaje":"38.02","entra":"si"},"1":{"id":"014","nombre":"PARTIDO OBRERO","fuerza_politica":"a definir por pablo","votos":1061,"porcentaje":"8.52","entra":"si"},"2":{"id":"002","nombre":"PARTIDO JUSTICIALISTA","fuerza_politica":"a definir por pablo","votos":1034,"porcentaje":"8.31","entra":"si","internas":[{"lista":"3085","nombre":"LISTA:  LEALTAD 17 DE OCTUBRE - LETRA:  C","votos":631,"porcentaje":"61.03"},{"lista":"3084","nombre":"LISTA:  EL CAMBIO SOMOS NOSOTROS  - LETRA:  B","votos":403,"porcentaje":"38.97"}]},"3":{"id":"200","nombre":"MEMORIA Y MOVILIZACION SOCIAL","fuerza_politica":"a definir por pablo","votos":721,"porcentaje":"5.79","entra":"si"},"4":{"id":"203","nombre":"SALTA SOMOS TODOS","fuerza_politica":"a definir por pablo","votos":578,"porcentaje":"4.64","entra":"si"},"5":{"id":"038","nombre":"MOVIMIENTO SOCIALISTA DE LOS TRABAJADORES (MST)","fuerza_politica":"a definir por pablo","votos":575,"porcentaje":"4.62","entra":"si"},"6":{"id":"155","nombre":"PARTIDO RENOVADOR DE SALTA","fuerza_politica":"a definir por pablo","votos":510,"porcentaje":"4.10","entra":"si"},"7":{"id":"060","nombre":"MOVIMIENTO INDEPENDIENTE JUSTICIA Y DIGNIDAD","fuerza_politica":"a definir por pablo","votos":498,"porcentaje":"4.00","entra":"si"},"8":{"id":"216","nombre":"FRENTE PLURAL","fuerza_politica":"a definir por pablo","votos":469,"porcentaje":"3.77","entra":"si"},"9":{"id":"054","nombre":"PARTIDO DE LA VICTORIA","fuerza_politica":"a definir por pablo","votos":397,"porcentaje":"3.19","entra":"si"},"10":{"id":"535","nombre":"FRENTE POPULAR SALTE\u00d1O","fuerza_politica":"a definir por pablo","votos":290,"porcentaje":"2.33","entra":"si"},"blanco":{"id":"blanco","votos":1583,"porcentaje":"10.77"},"nulos":{"id":"nulos","votos":705,"porcentaje":"4.80"},"recurridos":{"id":"recurridos","votos":1545,"porcentaje":"10.51"}}}},"SAL007":{"nombre":"Or\u00e1n","id":"007","votacion":{"mesas":{"total":268,"escrutadas":268,"porcentaje":100},"votos":{"total":68882,"escrutados":90602,"porcentaje":100},"partidos_politicos":{"0":{"id":"536","nombre":"UNION POR LA REPUBLICA - FRENTE POR LA JUSTICIA","fuerza_politica":"a definir por pablo","votos":21917,"porcentaje":"37.60","entra":"si"},"1":{"id":"014","nombre":"PARTIDO OBRERO","fuerza_politica":"a definir por pablo","votos":5000,"porcentaje":"8.58","entra":"si"},"2":{"id":"002","nombre":"PARTIDO JUSTICIALISTA","fuerza_politica":"a definir por pablo","votos":4991,"porcentaje":"8.56","entra":"si","internas":[{"lista":"3085","nombre":"LISTA:  LEALTAD 17 DE OCTUBRE - LETRA:  C","votos":3062,"porcentaje":"61.35"},{"lista":"3084","nombre":"LISTA:  EL CAMBIO SOMOS NOSOTROS  - LETRA:  B","votos":1929,"porcentaje":"38.65"}]},"3":{"id":"200","nombre":"MEMORIA Y MOVILIZACION SOCIAL","fuerza_politica":"a definir por pablo","votos":3401,"porcentaje":"5.83","entra":"si"},"4":{"id":"038","nombre":"MOVIMIENTO SOCIALISTA DE LOS TRABAJADORES (MST)","fuerza_politica":"a definir por pablo","votos":2713,"porcentaje":"4.65","entra":"si"},"5":{"id":"203","nombre":"SALTA SOMOS TODOS","fuerza_politica":"a definir por pablo","votos":2684,"porcentaje":"4.60","entra":"si"},"6":{"id":"155","nombre":"PARTIDO RENOVADOR DE SALTA","fuerza_politica":"a definir por pablo","votos":2420,"porcentaje":"4.15","entra":"si"},"7":{"id":"060","nombre":"MOVIMIENTO INDEPENDIENTE JUSTICIA Y DIGNIDAD","fuerza_politica":"a definir por pablo","votos":2321,"porcentaje":"3.98","entra":"si"},"8":{"id":"216","nombre":"FRENTE PLURAL","fuerza_politica":"a definir por pablo","votos":2166,"porcentaje":"3.72","entra":"si"},"9":{"id":"054","nombre":"PARTIDO DE LA VICTORIA","fuerza_politica":"a definir por pablo","votos":1842,"porcentaje":"3.16","entra":"si"},"10":{"id":"535","nombre":"FRENTE POPULAR SALTE\u00d1O","fuerza_politica":"a definir por pablo","votos":1389,"porcentaje":"2.38","entra":"si"},"blanco":{"id":"blanco","votos":7449,"porcentaje":"10.81"},"nulos":{"id":"nulos","votos":3312,"porcentaje":"4.81"},"recurridos":{"id":"recurridos","votos":7277,"porcentaje":"10.56"}}}},"SAL008":{"nombre":"San Mart\u00edn","id":"008","votacion":{"mesas":{"total":311,"escrutadas":311,"porcentaje":100},"votos":{"total":80279,"escrutados":105560,"porcentaje":100},"partidos_politicos":{"0":{"id":"536","nombre":"UNION POR LA REPUBLICA - FRENTE POR LA JUSTICIA","fuerza_politica":"a definir por pablo","votos":25621,"porcentaje":"37.71","entra":"si"},"1":{"id":"014","nombre":"PARTIDO OBRERO","fuerza_politica":"a definir por pablo","votos":5827,"porcentaje":"8.58","entra":"si"},"2":{"id":"002","nombre":"PARTIDO JUSTICIALISTA","fuerza_politica":"a definir por pablo","votos":5756,"porcentaje":"8.47","entra":"si","internas":[{"lista":"3085","nombre":"LISTA:  LEALTAD 17 DE OCTUBRE - LETRA:  C","votos":3533,"porcentaje":"61.38"},{"lista":"3084","nombre":"LISTA:  EL CAMBIO SOMOS NOSOTROS  - LETRA:  B","votos":2223,"porcentaje":"38.62"}]},"3":{"id":"200","nombre":"MEMORIA Y MOVILIZACION SOCIAL","fuerza_politica":"a definir por pablo","votos":3968,"porcentaje":"5.84","entra":"si"},"4":{"id":"038","nombre":"MOVIMIENTO SOCIALISTA DE LOS TRABAJADORES (MST)","fuerza_politica":"a definir por pablo","votos":3157,"porcentaje":"4.65","entra":"si"},"5":{"id":"203","nombre":"SALTA SOMOS TODOS","fuerza_politica":"a definir por pablo","votos":3049,"porcentaje":"4.49","entra":"si"},"6":{"id":"155","nombre":"PARTIDO RENOVADOR DE SALTA","fuerza_politica":"a definir por pablo","votos":2822,"porcentaje":"4.15","entra":"si"},"7":{"id":"060","nombre":"MOVIMIENTO INDEPENDIENTE JUSTICIA Y DIGNIDAD","fuerza_politica":"a definir por pablo","votos":2694,"porcentaje":"3.97","entra":"si"},"8":{"id":"216","nombre":"FRENTE PLURAL","fuerza_politica":"a definir por pablo","votos":2586,"porcentaje":"3.81","entra":"si"},"9":{"id":"054","nombre":"PARTIDO DE LA VICTORIA","fuerza_politica":"a definir por pablo","votos":2154,"porcentaje":"3.17","entra":"si"},"10":{"id":"535","nombre":"FRENTE POPULAR SALTE\u00d1O","fuerza_politica":"a definir por pablo","votos":1622,"porcentaje":"2.39","entra":"si"},"blanco":{"id":"blanco","votos":8682,"porcentaje":"10.81"},"nulos":{"id":"nulos","votos":3858,"porcentaje":"4.81"},"recurridos":{"id":"recurridos","votos":8483,"porcentaje":"10.57"}}}},"SAL009":{"nombre":"Iruya","id":"009","votacion":{"mesas":{"total":23,"escrutadas":23,"porcentaje":100},"votos":{"total":3313,"escrutados":4385,"porcentaje":100},"partidos_politicos":{"0":{"id":"536","nombre":"UNION POR LA REPUBLICA - FRENTE POR LA JUSTICIA","fuerza_politica":"a definir por pablo","votos":1111,"porcentaje":"39.48","entra":"si"},"1":{"id":"002","nombre":"PARTIDO JUSTICIALISTA","fuerza_politica":"a definir por pablo","votos":237,"porcentaje":"8.42","entra":"si","internas":[{"lista":"3085","nombre":"LISTA:  LEALTAD 17 DE OCTUBRE - LETRA:  C","votos":143,"porcentaje":"60.34"},{"lista":"3084","nombre":"LISTA:  EL CAMBIO SOMOS NOSOTROS  - LETRA:  B","votos":94,"porcentaje":"39.66"}]},"2":{"id":"014","nombre":"PARTIDO OBRERO","fuerza_politica":"a definir por pablo","votos":235,"porcentaje":"8.35","entra":"si"},"3":{"id":"200","nombre":"MEMORIA Y MOVILIZACION SOCIAL","fuerza_politica":"a definir por pablo","votos":159,"porcentaje":"5.65","entra":"si"},"4":{"id":"203","nombre":"SALTA SOMOS TODOS","fuerza_politica":"a definir por pablo","votos":135,"porcentaje":"4.80","entra":"si"},"5":{"id":"038","nombre":"MOVIMIENTO SOCIALISTA DE LOS TRABAJADORES (MST)","fuerza_politica":"a definir por pablo","votos":125,"porcentaje":"4.44","entra":"si"},"6":{"id":"155","nombre":"PARTIDO RENOVADOR DE SALTA","fuerza_politica":"a definir por pablo","votos":111,"porcentaje":"3.94","entra":"si"},"7":{"id":"060","nombre":"MOVIMIENTO INDEPENDIENTE JUSTICIA Y DIGNIDAD","fuerza_politica":"a definir por pablo","votos":106,"porcentaje":"3.77","entra":"si"},"8":{"id":"216","nombre":"FRENTE PLURAL","fuerza_politica":"a definir por pablo","votos":96,"porcentaje":"3.41","entra":"si"},"9":{"id":"054","nombre":"PARTIDO DE LA VICTORIA","fuerza_politica":"a definir por pablo","votos":82,"porcentaje":"2.91","entra":"si"},"10":{"id":"535","nombre":"FRENTE POPULAR SALTE\u00d1O","fuerza_politica":"a definir por pablo","votos":63,"porcentaje":"2.24","entra":"si"},"blanco":{"id":"blanco","votos":354,"porcentaje":"10.69"},"nulos":{"id":"nulos","votos":154,"porcentaje":"4.65"},"recurridos":{"id":"recurridos","votos":345,"porcentaje":"10.41"}}}},"SAL010":{"nombre":"Santa Victoria","id":"010","votacion":{"mesas":{"total":33,"escrutadas":33,"porcentaje":100},"votos":{"total":5840,"escrutados":7679,"porcentaje":100},"partidos_politicos":{"0":{"id":"536","nombre":"UNION POR LA REPUBLICA - FRENTE POR LA JUSTICIA","fuerza_politica":"a definir por pablo","votos":1969,"porcentaje":"39.72","entra":"si"},"1":{"id":"014","nombre":"PARTIDO OBRERO","fuerza_politica":"a definir por pablo","votos":423,"porcentaje":"8.53","entra":"si"},"2":{"id":"002","nombre":"PARTIDO JUSTICIALISTA","fuerza_politica":"a definir por pablo","votos":360,"porcentaje":"7.26","entra":"si","internas":[{"lista":"3085","nombre":"LISTA:  LEALTAD 17 DE OCTUBRE - LETRA:  C","votos":228,"porcentaje":"63.33"},{"lista":"3084","nombre":"LISTA:  EL CAMBIO SOMOS NOSOTROS  - LETRA:  B","votos":132,"porcentaje":"36.67"}]},"3":{"id":"200","nombre":"MEMORIA Y MOVILIZACION SOCIAL","fuerza_politica":"a definir por pablo","votos":285,"porcentaje":"5.75","entra":"si"},"4":{"id":"038","nombre":"MOVIMIENTO SOCIALISTA DE LOS TRABAJADORES (MST)","fuerza_politica":"a definir por pablo","votos":225,"porcentaje":"4.54","entra":"si"},"5":{"id":"203","nombre":"SALTA SOMOS TODOS","fuerza_politica":"a definir por pablo","votos":203,"porcentaje":"4.10","entra":"si"},"6":{"id":"155","nombre":"PARTIDO RENOVADOR DE SALTA","fuerza_politica":"a definir por pablo","votos":202,"porcentaje":"4.08","entra":"si"},"7":{"id":"216","nombre":"FRENTE PLURAL","fuerza_politica":"a definir por pablo","votos":200,"porcentaje":"4.03","entra":"si"},"8":{"id":"060","nombre":"MOVIMIENTO INDEPENDIENTE JUSTICIA Y DIGNIDAD","fuerza_politica":"a definir por pablo","votos":192,"porcentaje":"3.87","entra":"si"},"9":{"id":"054","nombre":"PARTIDO DE LA VICTORIA","fuerza_politica":"a definir por pablo","votos":156,"porcentaje":"3.15","entra":"si"},"10":{"id":"535","nombre":"FRENTE POPULAR SALTE\u00d1O","fuerza_politica":"a definir por pablo","votos":115,"porcentaje":"2.32","entra":"si"},"blanco":{"id":"blanco","votos":627,"porcentaje":"10.74"},"nulos":{"id":"nulos","votos":276,"porcentaje":"4.73"},"recurridos":{"id":"recurridos","votos":607,"porcentaje":"10.39"}}}},"SAL011":{"nombre":"Cerrillos","id":"011","votacion":{"mesas":{"total":67,"escrutadas":67,"porcentaje":100},"votos":{"total":16536,"escrutados":21784,"porcentaje":100},"partidos_politicos":{"0":{"id":"536","nombre":"UNION POR LA REPUBLICA - FRENTE POR LA JUSTICIA","fuerza_politica":"a definir por pablo","votos":5244,"porcentaje":"37.47","entra":"si"},"1":{"id":"002","nombre":"PARTIDO JUSTICIALISTA","fuerza_politica":"a definir por pablo","votos":1227,"porcentaje":"8.77","entra":"si","internas":[{"lista":"3085","nombre":"LISTA:  LEALTAD 17 DE OCTUBRE - LETRA:  C","votos":761,"porcentaje":"62.02"},{"lista":"3084","nombre":"LISTA:  EL CAMBIO SOMOS NOSOTROS  - LETRA:  B","votos":466,"porcentaje":"37.98"}]},"2":{"id":"014","nombre":"PARTIDO OBRERO","fuerza_politica":"a definir por pablo","votos":1199,"porcentaje":"8.57","entra":"si"},"3":{"id":"200","nombre":"MEMORIA Y MOVILIZACION SOCIAL","fuerza_politica":"a definir por pablo","votos":817,"porcentaje":"5.84","entra":"si"},"4":{"id":"203","nombre":"SALTA SOMOS TODOS","fuerza_politica":"a definir por pablo","votos":674,"porcentaje":"4.82","entra":"si"},"5":{"id":"038","nombre":"MOVIMIENTO SOCIALISTA DE LOS TRABAJADORES (MST)","fuerza_politica":"a definir por pablo","votos":661,"porcentaje":"4.72","entra":"si"},"6":{"id":"155","nombre":"PARTIDO RENOVADOR DE SALTA","fuerza_politica":"a definir por pablo","votos":581,"porcentaje":"4.15","entra":"si"},"7":{"id":"060","nombre":"MOVIMIENTO INDEPENDIENTE JUSTICIA Y DIGNIDAD","fuerza_politica":"a definir por pablo","votos":556,"porcentaje":"3.97","entra":"si"},"8":{"id":"216","nombre":"FRENTE PLURAL","fuerza_politica":"a definir por pablo","votos":480,"porcentaje":"3.43","entra":"si"},"9":{"id":"054","nombre":"PARTIDO DE LA VICTORIA","fuerza_politica":"a definir por pablo","votos":442,"porcentaje":"3.16","entra":"si"},"10":{"id":"535","nombre":"FRENTE POPULAR SALTE\u00d1O","fuerza_politica":"a definir por pablo","votos":332,"porcentaje":"2.37","entra":"si"},"blanco":{"id":"blanco","votos":1784,"porcentaje":"10.79"},"nulos":{"id":"nulos","votos":794,"porcentaje":"4.80"},"recurridos":{"id":"recurridos","votos":1745,"porcentaje":"10.55"}}}},"SAL012":{"nombre":"Chicoana","id":"012","votacion":{"mesas":{"total":46,"escrutadas":46,"porcentaje":100},"votos":{"total":10940,"escrutados":14393,"porcentaje":100},"partidos_politicos":{"0":{"id":"536","nombre":"UNION POR LA REPUBLICA - FRENTE POR LA JUSTICIA","fuerza_politica":"a definir por pablo","votos":3515,"porcentaje":"37.96","entra":"si"},"1":{"id":"014","nombre":"PARTIDO OBRERO","fuerza_politica":"a definir por pablo","votos":792,"porcentaje":"8.55","entra":"si"},"2":{"id":"002","nombre":"PARTIDO JUSTICIALISTA","fuerza_politica":"a definir por pablo","votos":778,"porcentaje":"8.40","entra":"si","internas":[{"lista":"3085","nombre":"LISTA:  LEALTAD 17 DE OCTUBRE - LETRA:  C","votos":474,"porcentaje":"60.93"},{"lista":"3084","nombre":"LISTA:  EL CAMBIO SOMOS NOSOTROS  - LETRA:  B","votos":304,"porcentaje":"39.07"}]},"3":{"id":"200","nombre":"MEMORIA Y MOVILIZACION SOCIAL","fuerza_politica":"a definir por pablo","votos":536,"porcentaje":"5.79","entra":"si"},"4":{"id":"038","nombre":"MOVIMIENTO SOCIALISTA DE LOS TRABAJADORES (MST)","fuerza_politica":"a definir por pablo","votos":426,"porcentaje":"4.60","entra":"si"},"5":{"id":"203","nombre":"SALTA SOMOS TODOS","fuerza_politica":"a definir por pablo","votos":411,"porcentaje":"4.44","entra":"si"},"6":{"id":"155","nombre":"PARTIDO RENOVADOR DE SALTA","fuerza_politica":"a definir por pablo","votos":383,"porcentaje":"4.14","entra":"si"},"7":{"id":"060","nombre":"MOVIMIENTO INDEPENDIENTE JUSTICIA Y DIGNIDAD","fuerza_politica":"a definir por pablo","votos":366,"porcentaje":"3.95","entra":"si"},"8":{"id":"216","nombre":"FRENTE PLURAL","fuerza_politica":"a definir por pablo","votos":359,"porcentaje":"3.88","entra":"si"},"9":{"id":"054","nombre":"PARTIDO DE LA VICTORIA","fuerza_politica":"a definir por pablo","votos":293,"porcentaje":"3.16","entra":"si"},"10":{"id":"535","nombre":"FRENTE POPULAR SALTE\u00d1O","fuerza_politica":"a definir por pablo","votos":218,"porcentaje":"2.35","entra":"si"},"blanco":{"id":"blanco","votos":1183,"porcentaje":"10.81"},"nulos":{"id":"nulos","votos":528,"porcentaje":"4.83"},"recurridos":{"id":"recurridos","votos":1152,"porcentaje":"10.53"}}}},"SAL013":{"nombre":"La Vi\u00f1a","id":"013","votacion":{"mesas":{"total":18,"escrutadas":18,"porcentaje":100},"votos":{"total":4411,"escrutados":5797,"porcentaje":100},"partidos_politicos":{"0":{"id":"536","nombre":"UNION POR LA REPUBLICA - FRENTE POR LA JUSTICIA","fuerza_politica":"a definir por pablo","votos":1425,"porcentaje":"38.15","entra":"si"},"1":{"id":"014","nombre":"PARTIDO OBRERO","fuerza_politica":"a definir por pablo","votos":320,"porcentaje":"8.57","entra":"si"},"2":{"id":"002","nombre":"PARTIDO JUSTICIALISTA","fuerza_politica":"a definir por pablo","votos":302,"porcentaje":"8.09","entra":"si","internas":[{"lista":"3085","nombre":"LISTA:  LEALTAD 17 DE OCTUBRE - LETRA:  C","votos":178,"porcentaje":"58.94"},{"lista":"3084","nombre":"LISTA:  EL CAMBIO SOMOS NOSOTROS  - LETRA:  B","votos":124,"porcentaje":"41.06"}]},"3":{"id":"200","nombre":"MEMORIA Y MOVILIZACION SOCIAL","fuerza_politica":"a definir por pablo","votos":217,"porcentaje":"5.81","entra":"si"},"4":{"id":"203","nombre":"SALTA SOMOS TODOS","fuerza_politica":"a definir por pablo","votos":168,"porcentaje":"4.50","entra":"si"},"5":{"id":"038","nombre":"MOVIMIENTO SOCIALISTA DE LOS TRABAJADORES (MST)","fuerza_politica":"a definir por pablo","votos":167,"porcentaje":"4.47","entra":"si"},"6":{"id":"155","nombre":"PARTIDO RENOVADOR DE SALTA","fuerza_politica":"a definir por pablo","votos":155,"porcentaje":"4.15","entra":"si"},"7":{"id":"216","nombre":"FRENTE PLURAL","fuerza_politica":"a definir por pablo","votos":147,"porcentaje":"3.94","entra":"si"},"8":{"id":"060","nombre":"MOVIMIENTO INDEPENDIENTE JUSTICIA Y DIGNIDAD","fuerza_politica":"a definir por pablo","votos":144,"porcentaje":"3.86","entra":"si"},"9":{"id":"054","nombre":"PARTIDO DE LA VICTORIA","fuerza_politica":"a definir por pablo","votos":125,"porcentaje":"3.35","entra":"si"},"10":{"id":"535","nombre":"FRENTE POPULAR SALTE\u00d1O","fuerza_politica":"a definir por pablo","votos":89,"porcentaje":"2.38","entra":"si"},"blanco":{"id":"blanco","votos":476,"porcentaje":"10.79"},"nulos":{"id":"nulos","votos":212,"porcentaje":"4.81"},"recurridos":{"id":"recurridos","votos":464,"porcentaje":"10.52"}}}},"SAL014":{"nombre":"Guachipas","id":"014","votacion":{"mesas":{"total":12,"escrutadas":12,"porcentaje":100},"votos":{"total":2078,"escrutados":2743,"porcentaje":100},"partidos_politicos":{"0":{"id":"536","nombre":"UNION POR LA REPUBLICA - FRENTE POR LA JUSTICIA","fuerza_politica":"a definir por pablo","votos":665,"porcentaje":"37.74","entra":"si"},"1":{"id":"002","nombre":"PARTIDO JUSTICIALISTA","fuerza_politica":"a definir por pablo","votos":168,"porcentaje":"9.53","entra":"si","internas":[{"lista":"3085","nombre":"LISTA:  LEALTAD 17 DE OCTUBRE - LETRA:  C","votos":105,"porcentaje":"62.50"},{"lista":"3084","nombre":"LISTA:  EL CAMBIO SOMOS NOSOTROS  - LETRA:  B","votos":63,"porcentaje":"37.50"}]},"2":{"id":"014","nombre":"PARTIDO OBRERO","fuerza_politica":"a definir por pablo","votos":151,"porcentaje":"8.57","entra":"si"},"3":{"id":"200","nombre":"MEMORIA Y MOVILIZACION SOCIAL","fuerza_politica":"a definir por pablo","votos":100,"porcentaje":"5.68","entra":"si"},"4":{"id":"203","nombre":"SALTA SOMOS TODOS","fuerza_politica":"a definir por pablo","votos":88,"porcentaje":"4.99","entra":"si"},"5":{"id":"038","nombre":"MOVIMIENTO SOCIALISTA DE LOS TRABAJADORES (MST)","fuerza_politica":"a definir por pablo","votos":87,"porcentaje":"4.94","entra":"si"},"6":{"id":"155","nombre":"PARTIDO RENOVADOR DE SALTA","fuerza_politica":"a definir por pablo","votos":73,"porcentaje":"4.14","entra":"si"},"7":{"id":"060","nombre":"MOVIMIENTO INDEPENDIENTE JUSTICIA Y DIGNIDAD","fuerza_politica":"a definir por pablo","votos":65,"porcentaje":"3.69","entra":"si"},"8":{"id":"054","nombre":"PARTIDO DE LA VICTORIA","fuerza_politica":"a definir por pablo","votos":53,"porcentaje":"3.01","entra":"si"},"9":{"id":"216","nombre":"FRENTE PLURAL","fuerza_politica":"a definir por pablo","votos":51,"porcentaje":"2.89","entra":"si"},"10":{"id":"535","nombre":"FRENTE POPULAR SALTE\u00d1O","fuerza_politica":"a definir por pablo","votos":39,"porcentaje":"2.21","entra":"si"},"blanco":{"id":"blanco","votos":222,"porcentaje":"10.68"},"nulos":{"id":"nulos","votos":99,"porcentaje":"4.76"},"recurridos":{"id":"recurridos","votos":217,"porcentaje":"10.44"}}}},"SAL015":{"nombre":"Rosario de la Frontera","id":"015","votacion":{"mesas":{"total":72,"escrutadas":72,"porcentaje":100},"votos":{"total":16176,"escrutados":21278,"porcentaje":100},"partidos_politicos":{"0":{"id":"536","nombre":"UNION POR LA REPUBLICA - FRENTE POR LA JUSTICIA","fuerza_politica":"a definir por pablo","votos":5178,"porcentaje":"37.78","entra":"si"},"1":{"id":"002","nombre":"PARTIDO JUSTICIALISTA","fuerza_politica":"a definir por pablo","votos":1200,"porcentaje":"8.76","entra":"si","internas":[{"lista":"3085","nombre":"LISTA:  LEALTAD 17 DE OCTUBRE - LETRA:  C","votos":735,"porcentaje":"61.25"},{"lista":"3084","nombre":"LISTA:  EL CAMBIO SOMOS NOSOTROS  - LETRA:  B","votos":465,"porcentaje":"38.75"}]},"2":{"id":"014","nombre":"PARTIDO OBRERO","fuerza_politica":"a definir por pablo","votos":1169,"porcentaje":"8.53","entra":"si"},"3":{"id":"200","nombre":"MEMORIA Y MOVILIZACION SOCIAL","fuerza_politica":"a definir por pablo","votos":797,"porcentaje":"5.81","entra":"si"},"4":{"id":"038","nombre":"MOVIMIENTO SOCIALISTA DE LOS TRABAJADORES (MST)","fuerza_politica":"a definir por pablo","votos":638,"porcentaje":"4.65","entra":"si"},"5":{"id":"203","nombre":"SALTA SOMOS TODOS","fuerza_politica":"a definir por pablo","votos":624,"porcentaje":"4.55","entra":"si"},"6":{"id":"155","nombre":"PARTIDO RENOVADOR DE SALTA","fuerza_politica":"a definir por pablo","votos":563,"porcentaje":"4.11","entra":"si"},"7":{"id":"060","nombre":"MOVIMIENTO INDEPENDIENTE JUSTICIA Y DIGNIDAD","fuerza_politica":"a definir por pablo","votos":543,"porcentaje":"3.96","entra":"si"},"8":{"id":"216","nombre":"FRENTE PLURAL","fuerza_politica":"a definir por pablo","votos":499,"porcentaje":"3.64","entra":"si"},"9":{"id":"054","nombre":"PARTIDO DE LA VICTORIA","fuerza_politica":"a definir por pablo","votos":427,"porcentaje":"3.12","entra":"si"},"10":{"id":"535","nombre":"FRENTE POPULAR SALTE\u00d1O","fuerza_politica":"a definir por pablo","votos":323,"porcentaje":"2.36","entra":"si"},"blanco":{"id":"blanco","votos":1745,"porcentaje":"10.79"},"nulos":{"id":"nulos","votos":771,"porcentaje":"4.77"},"recurridos":{"id":"recurridos","votos":1699,"porcentaje":"10.50"}}}},"SAL016":{"nombre":"La Candelaria","id":"016","votacion":{"mesas":{"total":16,"escrutadas":16,"porcentaje":100},"votos":{"total":3576,"escrutados":4714,"porcentaje":100},"partidos_politicos":{"0":{"id":"536","nombre":"UNION POR LA REPUBLICA - FRENTE POR LA JUSTICIA","fuerza_politica":"a definir por pablo","votos":1139,"porcentaje":"37.60","entra":"si"},"1":{"id":"014","nombre":"PARTIDO OBRERO","fuerza_politica":"a definir por pablo","votos":259,"porcentaje":"8.55","entra":"si"},"2":{"id":"002","nombre":"PARTIDO JUSTICIALISTA","fuerza_politica":"a definir por pablo","votos":243,"porcentaje":"8.02","entra":"si","internas":[{"lista":"3085","nombre":"LISTA:  LEALTAD 17 DE OCTUBRE - LETRA:  C","votos":159,"porcentaje":"65.43"},{"lista":"3084","nombre":"LISTA:  EL CAMBIO SOMOS NOSOTROS  - LETRA:  B","votos":84,"porcentaje":"34.57"}]},"3":{"id":"200","nombre":"MEMORIA Y MOVILIZACION SOCIAL","fuerza_politica":"a definir por pablo","votos":178,"porcentaje":"5.88","entra":"si"},"4":{"id":"203","nombre":"SALTA SOMOS TODOS","fuerza_politica":"a definir por pablo","votos":155,"porcentaje":"5.12","entra":"si"},"5":{"id":"038","nombre":"MOVIMIENTO SOCIALISTA DE LOS TRABAJADORES (MST)","fuerza_politica":"a definir por pablo","votos":152,"porcentaje":"5.02","entra":"si"},"6":{"id":"155","nombre":"PARTIDO RENOVADOR DE SALTA","fuerza_politica":"a definir por pablo","votos":126,"porcentaje":"4.16","entra":"si"},"7":{"id":"060","nombre":"MOVIMIENTO INDEPENDIENTE JUSTICIA Y DIGNIDAD","fuerza_politica":"a definir por pablo","votos":125,"porcentaje":"4.13","entra":"si"},"8":{"id":"216","nombre":"FRENTE PLURAL","fuerza_politica":"a definir por pablo","votos":100,"porcentaje":"3.30","entra":"si"},"9":{"id":"054","nombre":"PARTIDO DE LA VICTORIA","fuerza_politica":"a definir por pablo","votos":93,"porcentaje":"3.07","entra":"si"},"10":{"id":"535","nombre":"FRENTE POPULAR SALTE\u00d1O","fuerza_politica":"a definir por pablo","votos":71,"porcentaje":"2.34","entra":"si"},"blanco":{"id":"blanco","votos":388,"porcentaje":"10.85"},"nulos":{"id":"nulos","votos":170,"porcentaje":"4.75"},"recurridos":{"id":"recurridos","votos":377,"porcentaje":"10.54"}}}},"SAL017":{"nombre":"Cafayate","id":"017","votacion":{"mesas":{"total":33,"escrutadas":33,"porcentaje":100},"votos":{"total":7799,"escrutados":10270,"porcentaje":100},"partidos_politicos":{"0":{"id":"536","nombre":"UNION POR LA REPUBLICA - FRENTE POR LA JUSTICIA","fuerza_politica":"a definir por pablo","votos":2498,"porcentaje":"37.81","entra":"si"},"1":{"id":"014","nombre":"PARTIDO OBRERO","fuerza_politica":"a definir por pablo","votos":567,"porcentaje":"8.58","entra":"si"},"2":{"id":"002","nombre":"PARTIDO JUSTICIALISTA","fuerza_politica":"a definir por pablo","votos":564,"porcentaje":"8.54","entra":"si","internas":[{"lista":"3085","nombre":"LISTA:  LEALTAD 17 DE OCTUBRE - LETRA:  C","votos":350,"porcentaje":"62.06"},{"lista":"3084","nombre":"LISTA:  EL CAMBIO SOMOS NOSOTROS  - LETRA:  B","votos":214,"porcentaje":"37.94"}]},"3":{"id":"200","nombre":"MEMORIA Y MOVILIZACION SOCIAL","fuerza_politica":"a definir por pablo","votos":386,"porcentaje":"5.84","entra":"si"},"4":{"id":"203","nombre":"SALTA SOMOS TODOS","fuerza_politica":"a definir por pablo","votos":324,"porcentaje":"4.90","entra":"si"},"5":{"id":"038","nombre":"MOVIMIENTO SOCIALISTA DE LOS TRABAJADORES (MST)","fuerza_politica":"a definir por pablo","votos":287,"porcentaje":"4.34","entra":"si"},"6":{"id":"155","nombre":"PARTIDO RENOVADOR DE SALTA","fuerza_politica":"a definir por pablo","votos":273,"porcentaje":"4.13","entra":"si"},"7":{"id":"060","nombre":"MOVIMIENTO INDEPENDIENTE JUSTICIA Y DIGNIDAD","fuerza_politica":"a definir por pablo","votos":269,"porcentaje":"4.07","entra":"si"},"8":{"id":"216","nombre":"FRENTE PLURAL","fuerza_politica":"a definir por pablo","votos":231,"porcentaje":"3.50","entra":"si"},"9":{"id":"054","nombre":"PARTIDO DE LA VICTORIA","fuerza_politica":"a definir por pablo","votos":211,"porcentaje":"3.19","entra":"si"},"10":{"id":"535","nombre":"FRENTE POPULAR SALTE\u00d1O","fuerza_politica":"a definir por pablo","votos":156,"porcentaje":"2.36","entra":"si"},"blanco":{"id":"blanco","votos":840,"porcentaje":"10.77"},"nulos":{"id":"nulos","votos":373,"porcentaje":"4.78"},"recurridos":{"id":"recurridos","votos":820,"porcentaje":"10.51"}}}},"SAL018":{"nombre":"San Carlos","id":"018","votacion":{"mesas":{"total":18,"escrutadas":18,"porcentaje":100},"votos":{"total":3940,"escrutados":5157,"porcentaje":100},"partidos_politicos":{"0":{"id":"536","nombre":"UNION POR LA REPUBLICA - FRENTE POR LA JUSTICIA","fuerza_politica":"a definir por pablo","votos":1312,"porcentaje":"39.30","entra":"si"},"1":{"id":"014","nombre":"PARTIDO OBRERO","fuerza_politica":"a definir por pablo","votos":284,"porcentaje":"8.51","entra":"si"},"2":{"id":"002","nombre":"PARTIDO JUSTICIALISTA","fuerza_politica":"a definir por pablo","votos":254,"porcentaje":"7.61","entra":"si","internas":[{"lista":"3085","nombre":"LISTA:  LEALTAD 17 DE OCTUBRE - LETRA:  C","votos":163,"porcentaje":"64.17"},{"lista":"3084","nombre":"LISTA:  EL CAMBIO SOMOS NOSOTROS  - LETRA:  B","votos":91,"porcentaje":"35.83"}]},"3":{"id":"200","nombre":"MEMORIA Y MOVILIZACION SOCIAL","fuerza_politica":"a definir por pablo","votos":193,"porcentaje":"5.78","entra":"si"},"4":{"id":"216","nombre":"FRENTE PLURAL","fuerza_politica":"a definir por pablo","votos":156,"porcentaje":"4.67","entra":"si"},"5":{"id":"038","nombre":"MOVIMIENTO SOCIALISTA DE LOS TRABAJADORES (MST)","fuerza_politica":"a definir por pablo","votos":152,"porcentaje":"4.55","entra":"si"},"6":{"id":"155","nombre":"PARTIDO RENOVADOR DE SALTA","fuerza_politica":"a definir por pablo","votos":137,"porcentaje":"4.10","entra":"si"},"7":{"id":"060","nombre":"MOVIMIENTO INDEPENDIENTE JUSTICIA Y DIGNIDAD","fuerza_politica":"a definir por pablo","votos":125,"porcentaje":"3.74","entra":"si"},"8":{"id":"203","nombre":"SALTA SOMOS TODOS","fuerza_politica":"a definir por pablo","votos":121,"porcentaje":"3.62","entra":"si"},"9":{"id":"054","nombre":"PARTIDO DE LA VICTORIA","fuerza_politica":"a definir por pablo","votos":100,"porcentaje":"3.00","entra":"si"},"10":{"id":"535","nombre":"FRENTE POPULAR SALTE\u00d1O","fuerza_politica":"a definir por pablo","votos":78,"porcentaje":"2.34","entra":"si"},"blanco":{"id":"blanco","votos":426,"porcentaje":"10.81"},"nulos":{"id":"nulos","votos":188,"porcentaje":"4.77"},"recurridos":{"id":"recurridos","votos":414,"porcentaje":"10.51"}}}},"SAL019":{"nombre":"Molinos","id":"019","votacion":{"mesas":{"total":16,"escrutadas":16,"porcentaje":100},"votos":{"total":3033,"escrutados":4013,"porcentaje":100},"partidos_politicos":{"0":{"id":"536","nombre":"UNION POR LA REPUBLICA - FRENTE POR LA JUSTICIA","fuerza_politica":"a definir por pablo","votos":922,"porcentaje":"35.85","entra":"si"},"1":{"id":"002","nombre":"PARTIDO JUSTICIALISTA","fuerza_politica":"a definir por pablo","votos":267,"porcentaje":"10.38","entra":"si","internas":[{"lista":"3085","nombre":"LISTA:  LEALTAD 17 DE OCTUBRE - LETRA:  C","votos":159,"porcentaje":"59.55"},{"lista":"3084","nombre":"LISTA:  EL CAMBIO SOMOS NOSOTROS  - LETRA:  B","votos":108,"porcentaje":"40.45"}]},"2":{"id":"014","nombre":"PARTIDO OBRERO","fuerza_politica":"a definir por pablo","votos":220,"porcentaje":"8.55","entra":"si"},"3":{"id":"200","nombre":"MEMORIA Y MOVILIZACION SOCIAL","fuerza_politica":"a definir por pablo","votos":150,"porcentaje":"5.83","entra":"si"},"4":{"id":"203","nombre":"SALTA SOMOS TODOS","fuerza_politica":"a definir por pablo","votos":142,"porcentaje":"5.52","entra":"si"},"5":{"id":"038","nombre":"MOVIMIENTO SOCIALISTA DE LOS TRABAJADORES (MST)","fuerza_politica":"a definir por pablo","votos":118,"porcentaje":"4.59","entra":"si"},"6":{"id":"155","nombre":"PARTIDO RENOVADOR DE SALTA","fuerza_politica":"a definir por pablo","votos":107,"porcentaje":"4.16","entra":"si"},"7":{"id":"060","nombre":"MOVIMIENTO INDEPENDIENTE JUSTICIA Y DIGNIDAD","fuerza_politica":"a definir por pablo","votos":104,"porcentaje":"4.04","entra":"si"},"8":{"id":"216","nombre":"FRENTE PLURAL","fuerza_politica":"a definir por pablo","votos":78,"porcentaje":"3.03","entra":"si"},"9":{"id":"054","nombre":"PARTIDO DE LA VICTORIA","fuerza_politica":"a definir por pablo","votos":77,"porcentaje":"2.99","entra":"si"},"10":{"id":"535","nombre":"FRENTE POPULAR SALTE\u00d1O","fuerza_politica":"a definir por pablo","votos":59,"porcentaje":"2.29","entra":"si"},"blanco":{"id":"blanco","votos":328,"porcentaje":"10.81"},"nulos":{"id":"nulos","votos":143,"porcentaje":"4.71"},"recurridos":{"id":"recurridos","votos":318,"porcentaje":"10.48"}}}},"SAL020":{"nombre":"Cachi","id":"020","votacion":{"mesas":{"total":20,"escrutadas":20,"porcentaje":100},"votos":{"total":4152,"escrutados":5472,"porcentaje":100},"partidos_politicos":{"0":{"id":"536","nombre":"UNION POR LA REPUBLICA - FRENTE POR LA JUSTICIA","fuerza_politica":"a definir por pablo","votos":1381,"porcentaje":"39.26","entra":"si"},"1":{"id":"014","nombre":"PARTIDO OBRERO","fuerza_politica":"a definir por pablo","votos":299,"porcentaje":"8.50","entra":"si"},"2":{"id":"002","nombre":"PARTIDO JUSTICIALISTA","fuerza_politica":"a definir por pablo","votos":261,"porcentaje":"7.42","entra":"si","internas":[{"lista":"3085","nombre":"LISTA:  LEALTAD 17 DE OCTUBRE - LETRA:  C","votos":157,"porcentaje":"60.15"},{"lista":"3084","nombre":"LISTA:  EL CAMBIO SOMOS NOSOTROS  - LETRA:  B","votos":104,"porcentaje":"39.85"}]},"3":{"id":"200","nombre":"MEMORIA Y MOVILIZACION SOCIAL","fuerza_politica":"a definir por pablo","votos":201,"porcentaje":"5.71","entra":"si"},"4":{"id":"203","nombre":"SALTA SOMOS TODOS","fuerza_politica":"a definir por pablo","votos":163,"porcentaje":"4.63","entra":"si"},"5":{"id":"038","nombre":"MOVIMIENTO SOCIALISTA DE LOS TRABAJADORES (MST)","fuerza_politica":"a definir por pablo","votos":156,"porcentaje":"4.43","entra":"si"},"6":{"id":"155","nombre":"PARTIDO RENOVADOR DE SALTA","fuerza_politica":"a definir por pablo","votos":144,"porcentaje":"4.09","entra":"si"},"7":{"id":"060","nombre":"MOVIMIENTO INDEPENDIENTE JUSTICIA Y DIGNIDAD","fuerza_politica":"a definir por pablo","votos":141,"porcentaje":"4.01","entra":"si"},"8":{"id":"216","nombre":"FRENTE PLURAL","fuerza_politica":"a definir por pablo","votos":127,"porcentaje":"3.61","entra":"si"},"9":{"id":"054","nombre":"PARTIDO DE LA VICTORIA","fuerza_politica":"a definir por pablo","votos":115,"porcentaje":"3.27","entra":"si"},"10":{"id":"535","nombre":"FRENTE POPULAR SALTE\u00d1O","fuerza_politica":"a definir por pablo","votos":82,"porcentaje":"2.33","entra":"si"},"blanco":{"id":"blanco","votos":448,"porcentaje":"10.79"},"nulos":{"id":"nulos","votos":199,"porcentaje":"4.79"},"recurridos":{"id":"recurridos","votos":435,"porcentaje":"10.48"}}}},"SAL021":{"nombre":"Rosario de Lerma","id":"021","votacion":{"mesas":{"total":81,"escrutadas":81,"porcentaje":100},"votos":{"total":19427,"escrutados":25586,"porcentaje":100},"partidos_politicos":{"0":{"id":"536","nombre":"UNION POR LA REPUBLICA - FRENTE POR LA JUSTICIA","fuerza_politica":"a definir por pablo","votos":6184,"porcentaje":"37.61","entra":"si"},"1":{"id":"014","nombre":"PARTIDO OBRERO","fuerza_politica":"a definir por pablo","votos":1408,"porcentaje":"8.56","entra":"si"},"2":{"id":"002","nombre":"PARTIDO JUSTICIALISTA","fuerza_politica":"a definir por pablo","votos":1392,"porcentaje":"8.47","entra":"si","internas":[{"lista":"3085","nombre":"LISTA:  LEALTAD 17 DE OCTUBRE - LETRA:  C","votos":863,"porcentaje":"62.00"},{"lista":"3084","nombre":"LISTA:  EL CAMBIO SOMOS NOSOTROS  - LETRA:  B","votos":529,"porcentaje":"38.00"}]},"3":{"id":"200","nombre":"MEMORIA Y MOVILIZACION SOCIAL","fuerza_politica":"a definir por pablo","votos":957,"porcentaje":"5.82","entra":"si"},"4":{"id":"203","nombre":"SALTA SOMOS TODOS","fuerza_politica":"a definir por pablo","votos":788,"porcentaje":"4.79","entra":"si"},"5":{"id":"038","nombre":"MOVIMIENTO SOCIALISTA DE LOS TRABAJADORES (MST)","fuerza_politica":"a definir por pablo","votos":778,"porcentaje":"4.73","entra":"si"},"6":{"id":"155","nombre":"PARTIDO RENOVADOR DE SALTA","fuerza_politica":"a definir por pablo","votos":682,"porcentaje":"4.15","entra":"si"},"7":{"id":"060","nombre":"MOVIMIENTO INDEPENDIENTE JUSTICIA Y DIGNIDAD","fuerza_politica":"a definir por pablo","votos":658,"porcentaje":"4.00","entra":"si"},"8":{"id":"216","nombre":"FRENTE PLURAL","fuerza_politica":"a definir por pablo","votos":587,"porcentaje":"3.57","entra":"si"},"9":{"id":"054","nombre":"PARTIDO DE LA VICTORIA","fuerza_politica":"a definir por pablo","votos":527,"porcentaje":"3.20","entra":"si"},"10":{"id":"535","nombre":"FRENTE POPULAR SALTE\u00d1O","fuerza_politica":"a definir por pablo","votos":389,"porcentaje":"2.37","entra":"si"},"blanco":{"id":"blanco","votos":2094,"porcentaje":"10.78"},"nulos":{"id":"nulos","votos":929,"porcentaje":"4.78"},"recurridos":{"id":"recurridos","votos":2054,"porcentaje":"10.57"}}}},"SAL022":{"nombre":"La Poma","id":"022","votacion":{"mesas":{"total":4,"escrutadas":4,"porcentaje":100},"votos":{"total":957,"escrutados":1267,"porcentaje":100},"partidos_politicos":{"0":{"id":"536","nombre":"UNION POR LA REPUBLICA - FRENTE POR LA JUSTICIA","fuerza_politica":"a definir por pablo","votos":308,"porcentaje":"38.07","entra":"si"},"1":{"id":"014","nombre":"PARTIDO OBRERO","fuerza_politica":"a definir por pablo","votos":69,"porcentaje":"8.53","entra":"si"},"2":{"id":"002","nombre":"PARTIDO JUSTICIALISTA","fuerza_politica":"a definir por pablo","votos":64,"porcentaje":"7.91","entra":"si","internas":[{"lista":"3085","nombre":"LISTA:  LEALTAD 17 DE OCTUBRE - LETRA:  C","votos":38,"porcentaje":"59.37"},{"lista":"3084","nombre":"LISTA:  EL CAMBIO SOMOS NOSOTROS  - LETRA:  B","votos":26,"porcentaje":"40.63"}]},"3":{"id":"200","nombre":"MEMORIA Y MOVILIZACION SOCIAL","fuerza_politica":"a definir por pablo","votos":47,"porcentaje":"5.81","entra":"si"},"4":{"id":"203","nombre":"SALTA SOMOS TODOS","fuerza_politica":"a definir por pablo","votos":39,"porcentaje":"4.82","entra":"si"},"5":{"id":"060","nombre":"MOVIMIENTO INDEPENDIENTE JUSTICIA Y DIGNIDAD","fuerza_politica":"a definir por pablo","votos":36,"porcentaje":"4.45","entra":"si"},"6":{"id":"216","nombre":"FRENTE PLURAL","fuerza_politica":"a definir por pablo","votos":35,"porcentaje":"4.33","entra":"si"},"7":{"id":"155","nombre":"PARTIDO RENOVADOR DE SALTA","fuerza_politica":"a definir por pablo","votos":34,"porcentaje":"4.20","entra":"si"},"8":{"id":"038","nombre":"MOVIMIENTO SOCIALISTA DE LOS TRABAJADORES (MST)","fuerza_politica":"a definir por pablo","votos":28,"porcentaje":"3.46","entra":"si"},"9":{"id":"054","nombre":"PARTIDO DE LA VICTORIA","fuerza_politica":"a definir por pablo","votos":26,"porcentaje":"3.21","entra":"si"},"10":{"id":"535","nombre":"FRENTE POPULAR SALTE\u00d1O","fuerza_politica":"a definir por pablo","votos":19,"porcentaje":"2.35","entra":"si"},"blanco":{"id":"blanco","votos":104,"porcentaje":"10.87"},"nulos":{"id":"nulos","votos":46,"porcentaje":"4.81"},"recurridos":{"id":"recurridos","votos":102,"porcentaje":"10.66"}}}},"SAL023":{"nombre":"Los Andes","id":"023","votacion":{"mesas":{"total":16,"escrutadas":16,"porcentaje":100},"votos":{"total":3412,"escrutados":4498,"porcentaje":100},"partidos_politicos":{"0":{"id":"536","nombre":"UNION POR LA REPUBLICA - FRENTE POR LA JUSTICIA","fuerza_politica":"a definir por pablo","votos":1063,"porcentaje":"36.77","entra":"si"},"1":{"id":"002","nombre":"PARTIDO JUSTICIALISTA","fuerza_politica":"a definir por pablo","votos":261,"porcentaje":"9.03","entra":"si","internas":[{"lista":"3085","nombre":"LISTA:  LEALTAD 17 DE OCTUBRE - LETRA:  C","votos":160,"porcentaje":"61.30"},{"lista":"3084","nombre":"LISTA:  EL CAMBIO SOMOS NOSOTROS  - LETRA:  B","votos":101,"porcentaje":"38.70"}]},"2":{"id":"014","nombre":"PARTIDO OBRERO","fuerza_politica":"a definir por pablo","votos":247,"porcentaje":"8.54","entra":"si"},"3":{"id":"200","nombre":"MEMORIA Y MOVILIZACION SOCIAL","fuerza_politica":"a definir por pablo","votos":167,"porcentaje":"5.78","entra":"si"},"4":{"id":"203","nombre":"SALTA SOMOS TODOS","fuerza_politica":"a definir por pablo","votos":159,"porcentaje":"5.50","entra":"si"},"5":{"id":"038","nombre":"MOVIMIENTO SOCIALISTA DE LOS TRABAJADORES (MST)","fuerza_politica":"a definir por pablo","votos":144,"porcentaje":"4.98","entra":"si"},"6":{"id":"060","nombre":"MOVIMIENTO INDEPENDIENTE JUSTICIA Y DIGNIDAD","fuerza_politica":"a definir por pablo","votos":120,"porcentaje":"4.15","entra":"si"},"7":{"id":"155","nombre":"PARTIDO RENOVADOR DE SALTA","fuerza_politica":"a definir por pablo","votos":118,"porcentaje":"4.08","entra":"si"},"8":{"id":"054","nombre":"PARTIDO DE LA VICTORIA","fuerza_politica":"a definir por pablo","votos":91,"porcentaje":"3.15","entra":"si"},"9":{"id":"216","nombre":"FRENTE PLURAL","fuerza_politica":"a definir por pablo","votos":85,"porcentaje":"2.94","entra":"si"},"10":{"id":"535","nombre":"FRENTE POPULAR SALTE\u00d1O","fuerza_politica":"a definir por pablo","votos":68,"porcentaje":"2.35","entra":"si"},"blanco":{"id":"blanco","votos":368,"porcentaje":"10.79"},"nulos":{"id":"nulos","votos":163,"porcentaje":"4.78"},"recurridos":{"id":"recurridos","votos":358,"porcentaje":"10.49"}}}}},"nombre":"Salta","id":"SAL","votacion":{"mesas":{"total":2494,"escrutadas":2494,"porcentaje":100},"votos":{"total":622735,"escrutados":819156,"porcentaje":100},"partidos_politicos":{"0":{"id":"536","nombre":"UNION POR LA REPUBLICA - FRENTE POR LA JUSTICIA","fuerza_politica":"a definir por pablo","votos":198636,"porcentaje":"37.69","entra":"si"},"1":{"id":"014","nombre":"PARTIDO OBRERO","fuerza_politica":"a definir por pablo","votos":45171,"porcentaje":"8.57","entra":"si"},"2":{"id":"002","nombre":"PARTIDO JUSTICIALISTA","fuerza_politica":"a definir por pablo","votos":44906,"porcentaje":"8.52","entra":"si","internas":[{"lista":"3085","nombre":"LISTA:  LEALTAD 17 DE OCTUBRE - LETRA:  C","votos":27541,"porcentaje":"61.33"},{"lista":"3084","nombre":"LISTA:  EL CAMBIO SOMOS NOSOTROS  - LETRA:  B","votos":17365,"porcentaje":"38.67"}]},"3":{"id":"200","nombre":"MEMORIA Y MOVILIZACION SOCIAL","fuerza_politica":"a definir por pablo","votos":30717,"porcentaje":"5.83","entra":"si"},"4":{"id":"038","nombre":"MOVIMIENTO SOCIALISTA DE LOS TRABAJADORES (MST)","fuerza_politica":"a definir por pablo","votos":24470,"porcentaje":"4.64","entra":"si"},"5":{"id":"203","nombre":"SALTA SOMOS TODOS","fuerza_politica":"a definir por pablo","votos":24161,"porcentaje":"4.58","entra":"si"},"6":{"id":"155","nombre":"PARTIDO RENOVADOR DE SALTA","fuerza_politica":"a definir por pablo","votos":21840,"porcentaje":"4.14","entra":"si"},"7":{"id":"060","nombre":"MOVIMIENTO INDEPENDIENTE JUSTICIA Y DIGNIDAD","fuerza_politica":"a definir por pablo","votos":20953,"porcentaje":"3.98","entra":"si"},"8":{"id":"216","nombre":"FRENTE PLURAL","fuerza_politica":"a definir por pablo","votos":19656,"porcentaje":"3.73","entra":"si"},"9":{"id":"054","nombre":"PARTIDO DE LA VICTORIA","fuerza_politica":"a definir por pablo","votos":16733,"porcentaje":"3.17","entra":"si"},"10":{"id":"535","nombre":"FRENTE POPULAR SALTE\u00d1O","fuerza_politica":"a definir por pablo","votos":12523,"porcentaje":"2.38","entra":"si"},"blanco":{"id":"blanco","votos":67302,"porcentaje":"10.81"},"nulos":{"id":"nulos","votos":29905,"porcentaje":"4.80"},"recurridos":{"id":"recurridos","votos":65762,"porcentaje":"10.56"}}}}