{"localidades":{"CAP001":{"nombre":"Comuna 1","id":"001","votacion":{"mesas":{"porcentaje":99.63},"votos":{"porcentaje":99.62},"partidos_politicos":[{"id":"503","nombre":"UNION PRO","fuerza_politica":"PRO","votos":40602,"porcentaje":"32.74"},{"id":"502","nombre":"UNEN","fuerza_politica":"FP","votos":35972,"porcentaje":"29.01"},{"id":"501","nombre":"FRENTE PARA LA VICTORIA","fuerza_politica":"K","votos":26914,"porcentaje":"21.70"},{"id":"505","nombre":"FRENTE DE IZQUIERDA Y DE LOS TRABAJADORES","fuerza_politica":"IZ","votos":4453,"porcentaje":"3.59"},{"id":"504","nombre":"COMPROMISO FEDERAL","fuerza_politica":"PJ","votos":2796,"porcentaje":"2.25"},{"id":"506","nombre":"CAMINO POPULAR","fuerza_politica":"OT","votos":2685,"porcentaje":"2.17"},{"id":"187","nombre":"AUTODETERMINACION Y LIBERTAD","fuerza_politica":"IZ","votos":2616,"porcentaje":"2.11"},{"id":"068","nombre":"NUEVA IZQUIERDA","fuerza_politica":"IZ","votos":1738,"porcentaje":"1.40"},{"id":"262","nombre":"EL MOVIMIENTO","fuerza_politica":"OT","votos":1345,"porcentaje":"1.08"},{"id":"234","nombre":"MOVIMIENTO AL SOCIALISMO","fuerza_politica":"IZ","votos":1104,"porcentaje":"0.89"},{"id":"325","nombre":"MOVIMIENTO UNIDAD DEL TRABAJO Y LA PRODUCCION","fuerza_politica":"PJ","votos":930,"porcentaje":"0.75"},{"id":"324","nombre":"PARTIDO FE","fuerza_politica":"PJ","votos":511,"porcentaje":"0.41"},{"id":"008","nombre":"PARTIDO FEDERAL","fuerza_politica":"OT","votos":392,"porcentaje":"0.32"},{"id":"blancos","votos":1947,"porcentaje":"1.57"},{"id":"nulos","votos":1898,"porcentaje":"1.51"},{"id":"recurridos","votos":79,"porcentaje":"0.06"}]}},"CAP002":{"nombre":"Comuna 2","id":"002","votacion":{"mesas":{"porcentaje":99.54},"votos":{"porcentaje":99.54},"partidos_politicos":[{"id":"503","nombre":"UNION PRO","fuerza_politica":"PRO","votos":41437,"porcentaje":"39.26"},{"id":"502","nombre":"UNEN","fuerza_politica":"FP","votos":40337,"porcentaje":"38.22"},{"id":"501","nombre":"FRENTE PARA LA VICTORIA","fuerza_politica":"K","votos":12174,"porcentaje":"11.53"},{"id":"505","nombre":"FRENTE DE IZQUIERDA Y DE LOS TRABAJADORES","fuerza_politica":"IZ","votos":2417,"porcentaje":"2.29"},{"id":"506","nombre":"CAMINO POPULAR","fuerza_politica":"OT","votos":1979,"porcentaje":"1.87"},{"id":"187","nombre":"AUTODETERMINACION Y LIBERTAD","fuerza_politica":"IZ","votos":1534,"porcentaje":"1.45"},{"id":"504","nombre":"COMPROMISO FEDERAL","fuerza_politica":"PJ","votos":1515,"porcentaje":"1.44"},{"id":"068","nombre":"NUEVA IZQUIERDA","fuerza_politica":"IZ","votos":717,"porcentaje":"0.68"},{"id":"262","nombre":"EL MOVIMIENTO","fuerza_politica":"OT","votos":585,"porcentaje":"0.55"},{"id":"325","nombre":"MOVIMIENTO UNIDAD DEL TRABAJO Y LA PRODUCCION","fuerza_politica":"PJ","votos":568,"porcentaje":"0.54"},{"id":"234","nombre":"MOVIMIENTO AL SOCIALISMO","fuerza_politica":"IZ","votos":514,"porcentaje":"0.49"},{"id":"324","nombre":"PARTIDO FE","fuerza_politica":"PJ","votos":264,"porcentaje":"0.25"},{"id":"008","nombre":"PARTIDO FEDERAL","fuerza_politica":"OT","votos":156,"porcentaje":"0.15"},{"id":"blancos","votos":1351,"porcentaje":"1.28"},{"id":"nulos","votos":1134,"porcentaje":"1.06"},{"id":"recurridos","votos":31,"porcentaje":"0.03"}]}},"CAP003":{"nombre":"Comuna 3","id":"003","votacion":{"mesas":{"porcentaje":99.79},"votos":{"porcentaje":99.8},"partidos_politicos":[{"id":"502","nombre":"UNEN","fuerza_politica":"FP","votos":35125,"porcentaje":"29.92"},{"id":"503","nombre":"UNION PRO","fuerza_politica":"PRO","votos":33634,"porcentaje":"28.65"},{"id":"501","nombre":"FRENTE PARA LA VICTORIA","fuerza_politica":"K","votos":26206,"porcentaje":"22.32"},{"id":"505","nombre":"FRENTE DE IZQUIERDA Y DE LOS TRABAJADORES","fuerza_politica":"IZ","votos":5143,"porcentaje":"4.38"},{"id":"506","nombre":"CAMINO POPULAR","fuerza_politica":"OT","votos":3224,"porcentaje":"2.75"},{"id":"187","nombre":"AUTODETERMINACION Y LIBERTAD","fuerza_politica":"IZ","votos":3009,"porcentaje":"2.56"},{"id":"504","nombre":"COMPROMISO FEDERAL","fuerza_politica":"PJ","votos":2870,"porcentaje":"2.44"},{"id":"068","nombre":"NUEVA IZQUIERDA","fuerza_politica":"IZ","votos":1816,"porcentaje":"1.55"},{"id":"262","nombre":"EL MOVIMIENTO","fuerza_politica":"OT","votos":1318,"porcentaje":"1.12"},{"id":"234","nombre":"MOVIMIENTO AL SOCIALISMO","fuerza_politica":"IZ","votos":1221,"porcentaje":"1.04"},{"id":"325","nombre":"MOVIMIENTO UNIDAD DEL TRABAJO Y LA PRODUCCION","fuerza_politica":"PJ","votos":832,"porcentaje":"0.71"},{"id":"324","nombre":"PARTIDO FE","fuerza_politica":"PJ","votos":478,"porcentaje":"0.41"},{"id":"008","nombre":"PARTIDO FEDERAL","fuerza_politica":"OT","votos":445,"porcentaje":"0.38"},{"id":"blancos","votos":2066,"porcentaje":"1.76"},{"id":"nulos","votos":1859,"porcentaje":"1.56"},{"id":"recurridos","votos":135,"porcentaje":"0.11"}]}},"CAP004":{"nombre":"Comuna 4","id":"004","votacion":{"mesas":{"porcentaje":99.22},"votos":{"porcentaje":99.22},"partidos_politicos":[{"id":"503","nombre":"UNION PRO","fuerza_politica":"PRO","votos":41690,"porcentaje":"31.79"},{"id":"501","nombre":"FRENTE PARA LA VICTORIA","fuerza_politica":"K","votos":33194,"porcentaje":"25.31"},{"id":"502","nombre":"UNEN","fuerza_politica":"FP","votos":31281,"porcentaje":"23.85"},{"id":"505","nombre":"FRENTE DE IZQUIERDA Y DE LOS TRABAJADORES","fuerza_politica":"IZ","votos":5481,"porcentaje":"4.18"},{"id":"504","nombre":"COMPROMISO FEDERAL","fuerza_politica":"PJ","votos":3714,"porcentaje":"2.83"},{"id":"187","nombre":"AUTODETERMINACION Y LIBERTAD","fuerza_politica":"IZ","votos":2992,"porcentaje":"2.28"},{"id":"506","nombre":"CAMINO POPULAR","fuerza_politica":"OT","votos":2801,"porcentaje":"2.14"},{"id":"068","nombre":"NUEVA IZQUIERDA","fuerza_politica":"IZ","votos":1978,"porcentaje":"1.51"},{"id":"262","nombre":"EL MOVIMIENTO","fuerza_politica":"OT","votos":1816,"porcentaje":"1.38"},{"id":"234","nombre":"MOVIMIENTO AL SOCIALISMO","fuerza_politica":"IZ","votos":1483,"porcentaje":"1.13"},{"id":"325","nombre":"MOVIMIENTO UNIDAD DEL TRABAJO Y LA PRODUCCION","fuerza_politica":"PJ","votos":1181,"porcentaje":"0.90"},{"id":"324","nombre":"PARTIDO FE","fuerza_politica":"PJ","votos":590,"porcentaje":"0.45"},{"id":"008","nombre":"PARTIDO FEDERAL","fuerza_politica":"OT","votos":478,"porcentaje":"0.36"},{"id":"blancos","votos":2482,"porcentaje":"1.89"},{"id":"nulos","votos":2105,"porcentaje":"1.58"},{"id":"recurridos","votos":119,"porcentaje":"0.09"}]}},"CAP005":{"nombre":"Comuna 5","id":"005","votacion":{"mesas":{"porcentaje":100},"votos":{"porcentaje":100},"partidos_politicos":[{"id":"502","nombre":"UNEN","fuerza_politica":"FP","votos":38262,"porcentaje":"32.27"},{"id":"503","nombre":"UNION PRO","fuerza_politica":"PRO","votos":31994,"porcentaje":"26.99"},{"id":"501","nombre":"FRENTE PARA LA VICTORIA","fuerza_politica":"K","votos":25957,"porcentaje":"21.89"},{"id":"505","nombre":"FRENTE DE IZQUIERDA Y DE LOS TRABAJADORES","fuerza_politica":"IZ","votos":4915,"porcentaje":"4.15"},{"id":"506","nombre":"CAMINO POPULAR","fuerza_politica":"OT","votos":3996,"porcentaje":"3.37"},{"id":"187","nombre":"AUTODETERMINACION Y LIBERTAD","fuerza_politica":"IZ","votos":3269,"porcentaje":"2.76"},{"id":"504","nombre":"COMPROMISO FEDERAL","fuerza_politica":"PJ","votos":2630,"porcentaje":"2.22"},{"id":"068","nombre":"NUEVA IZQUIERDA","fuerza_politica":"IZ","votos":1823,"porcentaje":"1.54"},{"id":"234","nombre":"MOVIMIENTO AL SOCIALISMO","fuerza_politica":"IZ","votos":1103,"porcentaje":"0.93"},{"id":"262","nombre":"EL MOVIMIENTO","fuerza_politica":"OT","votos":1067,"porcentaje":"0.90"},{"id":"325","nombre":"MOVIMIENTO UNIDAD DEL TRABAJO Y LA PRODUCCION","fuerza_politica":"PJ","votos":933,"porcentaje":"0.79"},{"id":"324","nombre":"PARTIDO FE","fuerza_politica":"PJ","votos":374,"porcentaje":"0.32"},{"id":"008","nombre":"PARTIDO FEDERAL","fuerza_politica":"OT","votos":291,"porcentaje":"0.25"},{"id":"blancos","votos":1945,"porcentaje":"1.64"},{"id":"nulos","votos":1607,"porcentaje":"1.34"},{"id":"recurridos","votos":85,"porcentaje":"0.07"}]}},"CAP006":{"nombre":"Comuna 6","id":"006","votacion":{"mesas":{"porcentaje":100},"votos":{"porcentaje":100},"partidos_politicos":[{"id":"502","nombre":"UNEN","fuerza_politica":"FP","votos":44461,"porcentaje":"36.22"},{"id":"503","nombre":"UNION PRO","fuerza_politica":"PRO","votos":35592,"porcentaje":"29.00"},{"id":"501","nombre":"FRENTE PARA LA VICTORIA","fuerza_politica":"K","votos":22151,"porcentaje":"18.05"},{"id":"505","nombre":"FRENTE DE IZQUIERDA Y DE LOS TRABAJADORES","fuerza_politica":"IZ","votos":4429,"porcentaje":"3.61"},{"id":"506","nombre":"CAMINO POPULAR","fuerza_politica":"OT","votos":4378,"porcentaje":"3.57"},{"id":"187","nombre":"AUTODETERMINACION Y LIBERTAD","fuerza_politica":"IZ","votos":3291,"porcentaje":"2.68"},{"id":"504","nombre":"COMPROMISO FEDERAL","fuerza_politica":"PJ","votos":1987,"porcentaje":"1.62"},{"id":"068","nombre":"NUEVA IZQUIERDA","fuerza_politica":"IZ","votos":1730,"porcentaje":"1.41"},{"id":"234","nombre":"MOVIMIENTO AL SOCIALISMO","fuerza_politica":"IZ","votos":894,"porcentaje":"0.73"},{"id":"325","nombre":"MOVIMIENTO UNIDAD DEL TRABAJO Y LA PRODUCCION","fuerza_politica":"PJ","votos":753,"porcentaje":"0.61"},{"id":"262","nombre":"EL MOVIMIENTO","fuerza_politica":"OT","votos":726,"porcentaje":"0.59"},{"id":"324","nombre":"PARTIDO FE","fuerza_politica":"PJ","votos":309,"porcentaje":"0.25"},{"id":"008","nombre":"PARTIDO FEDERAL","fuerza_politica":"OT","votos":236,"porcentaje":"0.19"},{"id":"blancos","votos":1806,"porcentaje":"1.47"},{"id":"nulos","votos":1685,"porcentaje":"1.35"},{"id":"recurridos","votos":89,"porcentaje":"0.07"}]}},"CAP007":{"nombre":"Comuna 7","id":"007","votacion":{"mesas":{"porcentaje":99.8},"votos":{"porcentaje":99.8},"partidos_politicos":[{"id":"502","nombre":"UNEN","fuerza_politica":"FP","votos":41062,"porcentaje":"31.66"},{"id":"503","nombre":"UNION PRO","fuerza_politica":"PRO","votos":37083,"porcentaje":"28.59"},{"id":"501","nombre":"FRENTE PARA LA VICTORIA","fuerza_politica":"K","votos":28110,"porcentaje":"21.67"},{"id":"505","nombre":"FRENTE DE IZQUIERDA Y DE LOS TRABAJADORES","fuerza_politica":"IZ","votos":5013,"porcentaje":"3.86"},{"id":"506","nombre":"CAMINO POPULAR","fuerza_politica":"OT","votos":3808,"porcentaje":"2.94"},{"id":"187","nombre":"AUTODETERMINACION Y LIBERTAD","fuerza_politica":"IZ","votos":3162,"porcentaje":"2.44"},{"id":"504","nombre":"COMPROMISO FEDERAL","fuerza_politica":"PJ","votos":2880,"porcentaje":"2.22"},{"id":"068","nombre":"NUEVA IZQUIERDA","fuerza_politica":"IZ","votos":2040,"porcentaje":"1.57"},{"id":"262","nombre":"EL MOVIMIENTO","fuerza_politica":"OT","votos":1284,"porcentaje":"0.99"},{"id":"234","nombre":"MOVIMIENTO AL SOCIALISMO","fuerza_politica":"IZ","votos":1211,"porcentaje":"0.93"},{"id":"325","nombre":"MOVIMIENTO UNIDAD DEL TRABAJO Y LA PRODUCCION","fuerza_politica":"PJ","votos":934,"porcentaje":"0.72"},{"id":"324","nombre":"PARTIDO FE","fuerza_politica":"PJ","votos":471,"porcentaje":"0.36"},{"id":"008","nombre":"PARTIDO FEDERAL","fuerza_politica":"OT","votos":414,"porcentaje":"0.32"},{"id":"blancos","votos":2241,"porcentaje":"1.73"},{"id":"nulos","votos":1981,"porcentaje":"1.50"},{"id":"recurridos","votos":165,"porcentaje":"0.13"}]}},"CAP008":{"nombre":"Comuna 8","id":"008","votacion":{"mesas":{"porcentaje":99.23},"votos":{"porcentaje":99.23},"partidos_politicos":[{"id":"503","nombre":"UNION PRO","fuerza_politica":"PRO","votos":30836,"porcentaje":"30.39"},{"id":"501","nombre":"FRENTE PARA LA VICTORIA","fuerza_politica":"K","votos":29465,"porcentaje":"29.04"},{"id":"502","nombre":"UNEN","fuerza_politica":"FP","votos":21340,"porcentaje":"21.03"},{"id":"505","nombre":"FRENTE DE IZQUIERDA Y DE LOS TRABAJADORES","fuerza_politica":"IZ","votos":3988,"porcentaje":"3.93"},{"id":"504","nombre":"COMPROMISO FEDERAL","fuerza_politica":"PJ","votos":3540,"porcentaje":"3.49"},{"id":"187","nombre":"AUTODETERMINACION Y LIBERTAD","fuerza_politica":"IZ","votos":2089,"porcentaje":"2.06"},{"id":"262","nombre":"EL MOVIMIENTO","fuerza_politica":"OT","votos":1610,"porcentaje":"1.59"},{"id":"506","nombre":"CAMINO POPULAR","fuerza_politica":"OT","votos":1564,"porcentaje":"1.54"},{"id":"068","nombre":"NUEVA IZQUIERDA","fuerza_politica":"IZ","votos":1393,"porcentaje":"1.37"},{"id":"325","nombre":"MOVIMIENTO UNIDAD DEL TRABAJO Y LA PRODUCCION","fuerza_politica":"PJ","votos":1237,"porcentaje":"1.22"},{"id":"234","nombre":"MOVIMIENTO AL SOCIALISMO","fuerza_politica":"IZ","votos":1167,"porcentaje":"1.15"},{"id":"324","nombre":"PARTIDO FE","fuerza_politica":"PJ","votos":818,"porcentaje":"0.81"},{"id":"008","nombre":"PARTIDO FEDERAL","fuerza_politica":"OT","votos":426,"porcentaje":"0.42"},{"id":"blancos","votos":2007,"porcentaje":"1.98"},{"id":"nulos","votos":1692,"porcentaje":"1.64"},{"id":"recurridos","votos":159,"porcentaje":"0.15"}]}},"CAP009":{"nombre":"Comuna 9","id":"009","votacion":{"mesas":{"porcentaje":99.53},"votos":{"porcentaje":99.53},"partidos_politicos":[{"id":"503","nombre":"UNION PRO","fuerza_politica":"PRO","votos":34242,"porcentaje":"30.07"},{"id":"502","nombre":"UNEN","fuerza_politica":"FP","votos":31963,"porcentaje":"28.07"},{"id":"501","nombre":"FRENTE PARA LA VICTORIA","fuerza_politica":"K","votos":26099,"porcentaje":"22.92"},{"id":"505","nombre":"FRENTE DE IZQUIERDA Y DE LOS TRABAJADORES","fuerza_politica":"IZ","votos":4537,"porcentaje":"3.98"},{"id":"504","nombre":"COMPROMISO FEDERAL","fuerza_politica":"PJ","votos":3458,"porcentaje":"3.04"},{"id":"187","nombre":"AUTODETERMINACION Y LIBERTAD","fuerza_politica":"IZ","votos":2827,"porcentaje":"2.48"},{"id":"506","nombre":"CAMINO POPULAR","fuerza_politica":"OT","votos":2546,"porcentaje":"2.24"},{"id":"068","nombre":"NUEVA IZQUIERDA","fuerza_politica":"IZ","votos":1957,"porcentaje":"1.72"},{"id":"262","nombre":"EL MOVIMIENTO","fuerza_politica":"OT","votos":1366,"porcentaje":"1.20"},{"id":"234","nombre":"MOVIMIENTO AL SOCIALISMO","fuerza_politica":"IZ","votos":1138,"porcentaje":"1.00"},{"id":"325","nombre":"MOVIMIENTO UNIDAD DEL TRABAJO Y LA PRODUCCION","fuerza_politica":"PJ","votos":852,"porcentaje":"0.75"},{"id":"008","nombre":"PARTIDO FEDERAL","fuerza_politica":"OT","votos":451,"porcentaje":"0.40"},{"id":"324","nombre":"PARTIDO FE","fuerza_politica":"PJ","votos":445,"porcentaje":"0.39"},{"id":"blancos","votos":1992,"porcentaje":"1.75"},{"id":"nulos","votos":1703,"porcentaje":"1.47"},{"id":"recurridos","votos":131,"porcentaje":"0.11"}]}},"CAP010":{"nombre":"Comuna 10","id":"010","votacion":{"mesas":{"porcentaje":99.77},"votos":{"porcentaje":99.77},"partidos_politicos":[{"id":"502","nombre":"UNEN","fuerza_politica":"FP","votos":36515,"porcentaje":"31.82"},{"id":"503","nombre":"UNION PRO","fuerza_politica":"PRO","votos":33710,"porcentaje":"29.37"},{"id":"501","nombre":"FRENTE PARA LA VICTORIA","fuerza_politica":"K","votos":23351,"porcentaje":"20.35"},{"id":"505","nombre":"FRENTE DE IZQUIERDA Y DE LOS TRABAJADORES","fuerza_politica":"IZ","votos":4527,"porcentaje":"3.94"},{"id":"187","nombre":"AUTODETERMINACION Y LIBERTAD","fuerza_politica":"IZ","votos":3246,"porcentaje":"2.83"},{"id":"506","nombre":"CAMINO POPULAR","fuerza_politica":"OT","votos":2930,"porcentaje":"2.55"},{"id":"504","nombre":"COMPROMISO FEDERAL","fuerza_politica":"PJ","votos":2776,"porcentaje":"2.42"},{"id":"068","nombre":"NUEVA IZQUIERDA","fuerza_politica":"IZ","votos":1997,"porcentaje":"1.74"},{"id":"262","nombre":"EL MOVIMIENTO","fuerza_politica":"OT","votos":1069,"porcentaje":"0.93"},{"id":"234","nombre":"MOVIMIENTO AL SOCIALISMO","fuerza_politica":"IZ","votos":1063,"porcentaje":"0.93"},{"id":"325","nombre":"MOVIMIENTO UNIDAD DEL TRABAJO Y LA PRODUCCION","fuerza_politica":"PJ","votos":759,"porcentaje":"0.66"},{"id":"324","nombre":"PARTIDO FE","fuerza_politica":"PJ","votos":419,"porcentaje":"0.37"},{"id":"008","nombre":"PARTIDO FEDERAL","fuerza_politica":"OT","votos":373,"porcentaje":"0.33"},{"id":"blancos","votos":2024,"porcentaje":"1.76"},{"id":"nulos","votos":1820,"porcentaje":"1.56"},{"id":"recurridos","votos":110,"porcentaje":"0.09"}]}},"CAP011":{"nombre":"Comuna 11","id":"011","votacion":{"mesas":{"porcentaje":99.59},"votos":{"porcentaje":99.59},"partidos_politicos":[{"id":"502","nombre":"UNEN","fuerza_politica":"FP","votos":45059,"porcentaje":"34.26"},{"id":"503","nombre":"UNION PRO","fuerza_politica":"PRO","votos":39926,"porcentaje":"30.35"},{"id":"501","nombre":"FRENTE PARA LA VICTORIA","fuerza_politica":"K","votos":24721,"porcentaje":"18.79"},{"id":"505","nombre":"FRENTE DE IZQUIERDA Y DE LOS TRABAJADORES","fuerza_politica":"IZ","votos":4837,"porcentaje":"3.68"},{"id":"187","nombre":"AUTODETERMINACION Y LIBERTAD","fuerza_politica":"IZ","votos":3567,"porcentaje":"2.71"},{"id":"506","nombre":"CAMINO POPULAR","fuerza_politica":"OT","votos":3196,"porcentaje":"2.43"},{"id":"504","nombre":"COMPROMISO FEDERAL","fuerza_politica":"PJ","votos":2665,"porcentaje":"2.03"},{"id":"068","nombre":"NUEVA IZQUIERDA","fuerza_politica":"IZ","votos":1767,"porcentaje":"1.34"},{"id":"234","nombre":"MOVIMIENTO AL SOCIALISMO","fuerza_politica":"IZ","votos":1158,"porcentaje":"0.88"},{"id":"262","nombre":"EL MOVIMIENTO","fuerza_politica":"OT","votos":1014,"porcentaje":"0.77"},{"id":"325","nombre":"MOVIMIENTO UNIDAD DEL TRABAJO Y LA PRODUCCION","fuerza_politica":"PJ","votos":759,"porcentaje":"0.58"},{"id":"324","nombre":"PARTIDO FE","fuerza_politica":"PJ","votos":366,"porcentaje":"0.28"},{"id":"008","nombre":"PARTIDO FEDERAL","fuerza_politica":"OT","votos":332,"porcentaje":"0.25"},{"id":"blancos","votos":2164,"porcentaje":"1.65"},{"id":"nulos","votos":1951,"porcentaje":"1.46"},{"id":"recurridos","votos":128,"porcentaje":"0.10"}]}},"CAP012":{"nombre":"Comuna 12","id":"012","votacion":{"mesas":{"porcentaje":99.81},"votos":{"porcentaje":99.81},"partidos_politicos":[{"id":"502","nombre":"UNEN","fuerza_politica":"FP","votos":46643,"porcentaje":"32.72"},{"id":"503","nombre":"UNION PRO","fuerza_politica":"PRO","votos":46564,"porcentaje":"32.67"},{"id":"501","nombre":"FRENTE PARA LA VICTORIA","fuerza_politica":"K","votos":26533,"porcentaje":"18.62"},{"id":"505","nombre":"FRENTE DE IZQUIERDA Y DE LOS TRABAJADORES","fuerza_politica":"IZ","votos":5327,"porcentaje":"3.74"},{"id":"506","nombre":"CAMINO POPULAR","fuerza_politica":"OT","votos":3512,"porcentaje":"2.46"},{"id":"187","nombre":"AUTODETERMINACION Y LIBERTAD","fuerza_politica":"IZ","votos":3483,"porcentaje":"2.44"},{"id":"504","nombre":"COMPROMISO FEDERAL","fuerza_politica":"PJ","votos":2754,"porcentaje":"1.93"},{"id":"068","nombre":"NUEVA IZQUIERDA","fuerza_politica":"IZ","votos":1791,"porcentaje":"1.26"},{"id":"234","nombre":"MOVIMIENTO AL SOCIALISMO","fuerza_politica":"IZ","votos":1109,"porcentaje":"0.78"},{"id":"262","nombre":"EL MOVIMIENTO","fuerza_politica":"OT","votos":1076,"porcentaje":"0.75"},{"id":"325","nombre":"MOVIMIENTO UNIDAD DEL TRABAJO Y LA PRODUCCION","fuerza_politica":"PJ","votos":843,"porcentaje":"0.59"},{"id":"324","nombre":"PARTIDO FE","fuerza_politica":"PJ","votos":390,"porcentaje":"0.27"},{"id":"008","nombre":"PARTIDO FEDERAL","fuerza_politica":"OT","votos":345,"porcentaje":"0.24"},{"id":"blancos","votos":2162,"porcentaje":"1.52"},{"id":"nulos","votos":1953,"porcentaje":"1.35"},{"id":"recurridos","votos":124,"porcentaje":"0.09"}]}},"CAP013":{"nombre":"Comuna 13","id":"013","votacion":{"mesas":{"porcentaje":99.2},"votos":{"porcentaje":99.2},"partidos_politicos":[{"id":"502","nombre":"UNEN","fuerza_politica":"FP","votos":60527,"porcentaje":"37.51"},{"id":"503","nombre":"UNION PRO","fuerza_politica":"PRO","votos":59174,"porcentaje":"36.67"},{"id":"501","nombre":"FRENTE PARA LA VICTORIA","fuerza_politica":"K","votos":21407,"porcentaje":"13.27"},{"id":"505","nombre":"FRENTE DE IZQUIERDA Y DE LOS TRABAJADORES","fuerza_politica":"IZ","votos":4462,"porcentaje":"2.77"},{"id":"506","nombre":"CAMINO POPULAR","fuerza_politica":"OT","votos":3775,"porcentaje":"2.34"},{"id":"187","nombre":"AUTODETERMINACION Y LIBERTAD","fuerza_politica":"IZ","votos":2959,"porcentaje":"1.83"},{"id":"504","nombre":"COMPROMISO FEDERAL","fuerza_politica":"PJ","votos":2231,"porcentaje":"1.38"},{"id":"068","nombre":"NUEVA IZQUIERDA","fuerza_politica":"IZ","votos":1482,"porcentaje":"0.92"},{"id":"234","nombre":"MOVIMIENTO AL SOCIALISMO","fuerza_politica":"IZ","votos":916,"porcentaje":"0.57"},{"id":"262","nombre":"EL MOVIMIENTO","fuerza_politica":"OT","votos":830,"porcentaje":"0.51"},{"id":"325","nombre":"MOVIMIENTO UNIDAD DEL TRABAJO Y LA PRODUCCION","fuerza_politica":"PJ","votos":822,"porcentaje":"0.51"},{"id":"324","nombre":"PARTIDO FE","fuerza_politica":"PJ","votos":331,"porcentaje":"0.21"},{"id":"008","nombre":"PARTIDO FEDERAL","fuerza_politica":"OT","votos":267,"porcentaje":"0.17"},{"id":"blancos","votos":2176,"porcentaje":"1.35"},{"id":"nulos","votos":1883,"porcentaje":"1.15"},{"id":"recurridos","votos":109,"porcentaje":"0.07"}]}},"CAP014":{"nombre":"Comuna 14","id":"014","votacion":{"mesas":{"porcentaje":99.67},"votos":{"porcentaje":99.67},"partidos_politicos":[{"id":"502","nombre":"UNEN","fuerza_politica":"FP","votos":57323,"porcentaje":"37.36"},{"id":"503","nombre":"UNION PRO","fuerza_politica":"PRO","votos":54162,"porcentaje":"35.30"},{"id":"501","nombre":"FRENTE PARA LA VICTORIA","fuerza_politica":"K","votos":22318,"porcentaje":"14.55"},{"id":"505","nombre":"FRENTE DE IZQUIERDA Y DE LOS TRABAJADORES","fuerza_politica":"IZ","votos":4382,"porcentaje":"2.86"},{"id":"506","nombre":"CAMINO POPULAR","fuerza_politica":"OT","votos":3699,"porcentaje":"2.41"},{"id":"187","nombre":"AUTODETERMINACION Y LIBERTAD","fuerza_politica":"IZ","votos":2589,"porcentaje":"1.69"},{"id":"504","nombre":"COMPROMISO FEDERAL","fuerza_politica":"PJ","votos":2228,"porcentaje":"1.45"},{"id":"068","nombre":"NUEVA IZQUIERDA","fuerza_politica":"IZ","votos":1431,"porcentaje":"0.93"},{"id":"234","nombre":"MOVIMIENTO AL SOCIALISMO","fuerza_politica":"IZ","votos":899,"porcentaje":"0.59"},{"id":"262","nombre":"EL MOVIMIENTO","fuerza_politica":"OT","votos":887,"porcentaje":"0.58"},{"id":"325","nombre":"MOVIMIENTO UNIDAD DEL TRABAJO Y LA PRODUCCION","fuerza_politica":"PJ","votos":840,"porcentaje":"0.55"},{"id":"324","nombre":"PARTIDO FE","fuerza_politica":"PJ","votos":315,"porcentaje":"0.21"},{"id":"008","nombre":"PARTIDO FEDERAL","fuerza_politica":"OT","votos":235,"porcentaje":"0.15"},{"id":"blancos","votos":2111,"porcentaje":"1.38"},{"id":"nulos","votos":1808,"porcentaje":"1.16"},{"id":"recurridos","votos":89,"porcentaje":"0.06"}]}},"CAP015":{"nombre":"Comuna 15","id":"015","votacion":{"mesas":{"porcentaje":99.58},"votos":{"porcentaje":99.58},"partidos_politicos":[{"id":"502","nombre":"UNEN","fuerza_politica":"FP","votos":39853,"porcentaje":"32.08"},{"id":"503","nombre":"UNION PRO","fuerza_politica":"PRO","votos":33299,"porcentaje":"26.81"},{"id":"501","nombre":"FRENTE PARA LA VICTORIA","fuerza_politica":"K","votos":27063,"porcentaje":"21.79"},{"id":"505","nombre":"FRENTE DE IZQUIERDA Y DE LOS TRABAJADORES","fuerza_politica":"IZ","votos":5480,"porcentaje":"4.41"},{"id":"506","nombre":"CAMINO POPULAR","fuerza_politica":"OT","votos":4187,"porcentaje":"3.37"},{"id":"187","nombre":"AUTODETERMINACION Y LIBERTAD","fuerza_politica":"IZ","votos":3843,"porcentaje":"3.09"},{"id":"504","nombre":"COMPROMISO FEDERAL","fuerza_politica":"PJ","votos":2716,"porcentaje":"2.19"},{"id":"068","nombre":"NUEVA IZQUIERDA","fuerza_politica":"IZ","votos":1893,"porcentaje":"1.52"},{"id":"234","nombre":"MOVIMIENTO AL SOCIALISMO","fuerza_politica":"IZ","votos":1273,"porcentaje":"1.02"},{"id":"262","nombre":"EL MOVIMIENTO","fuerza_politica":"OT","votos":1062,"porcentaje":"0.85"},{"id":"325","nombre":"MOVIMIENTO UNIDAD DEL TRABAJO Y LA PRODUCCION","fuerza_politica":"PJ","votos":865,"porcentaje":"0.70"},{"id":"324","nombre":"PARTIDO FE","fuerza_politica":"PJ","votos":337,"porcentaje":"0.27"},{"id":"008","nombre":"PARTIDO FEDERAL","fuerza_politica":"OT","votos":292,"porcentaje":"0.24"},{"id":"blancos","votos":2051,"porcentaje":"1.65"},{"id":"nulos","votos":1903,"porcentaje":"1.51"},{"id":"recurridos","votos":148,"porcentaje":"0.12"}]}}},"nombre":"Ciudad Aut\u00f3noma Bs.As.","id":"CAP","votacion":{"mesas":{"porcentaje":99.62},"votos":{"porcentaje":99.62},"partidos_politicos":[{"id":"502","nombre":"UNEN","fuerza_politica":"FP","votos":605723,"porcentaje":"32.01"},{"id":"503","nombre":"UNION PRO","fuerza_politica":"PRO","votos":593945,"porcentaje":"31.39"},{"id":"501","nombre":"FRENTE PARA LA VICTORIA","fuerza_politica":"K","votos":375663,"porcentaje":"19.85"},{"id":"505","nombre":"FRENTE DE IZQUIERDA Y DE LOS TRABAJADORES","fuerza_politica":"IZ","votos":69391,"porcentaje":"3.67"},{"id":"506","nombre":"CAMINO POPULAR","fuerza_politica":"OT","votos":48280,"porcentaje":"2.55"},{"id":"187","nombre":"AUTODETERMINACION Y LIBERTAD","fuerza_politica":"IZ","votos":44476,"porcentaje":"2.35"},{"id":"504","nombre":"COMPROMISO FEDERAL","fuerza_politica":"PJ","votos":40760,"porcentaje":"2.15"},{"id":"068","nombre":"NUEVA IZQUIERDA","fuerza_politica":"IZ","votos":25553,"porcentaje":"1.35"},{"id":"262","nombre":"EL MOVIMIENTO","fuerza_politica":"OT","votos":17055,"porcentaje":"0.90"},{"id":"234","nombre":"MOVIMIENTO AL SOCIALISMO","fuerza_politica":"IZ","votos":16253,"porcentaje":"0.86"},{"id":"325","nombre":"MOVIMIENTO UNIDAD DEL TRABAJO Y LA PRODUCCION","fuerza_politica":"PJ","votos":13108,"porcentaje":"0.69"},{"id":"324","nombre":"PARTIDO FE","fuerza_politica":"PJ","votos":6418,"porcentaje":"0.34"},{"id":"008","nombre":"PARTIDO FEDERAL","fuerza_politica":"OT","votos":5133,"porcentaje":"0.27"},{"id":"blancos","votos":30525,"porcentaje":"1.61"},{"id":"nulos","votos":26982,"porcentaje":"1.40"},{"id":"recurridos","votos":1701,"porcentaje":"0.09"}]}}